{"NBAT":{
 "execution_paths": "53", 
 "callstack": false, 
 "reentrancy": false, 
 "modulo": false, 
 "division": false, 
 "execution_time": "19.3546020985", 
 "signedness": false, 
 "evm_code_coverage": "100.0", 
 "underflow": false, 
 "time_dependency": false, 
 "assertion_failure": false, 
 "timeout": false, 
 "dead_code": [
  "STOP "
 ], 
 "overflow": "\n../contractSrc/0x9a7a4ea93ce5a9129d754b7dbeb3a3968939d6b3.sol:NBAT:46:9\nbalances[_to] += _value\n^\n../contractSrc/0x9a7a4ea93ce5a9129d754b7dbeb3a3968939d6b3.sol:NBAT:56:9\nbalances[_to] += _value\n^", 
 "money_concurrency": false, 
 "truncation": false
},"SafeMath":{
 "execution_paths": "1", 
 "callstack": false, 
 "reentrancy": false, 
 "modulo": false, 
 "division": false, 
 "execution_time": "0.00508999824524", 
 "signedness": false, 
 "evm_code_coverage": "100.0", 
 "underflow": false, 
 "time_dependency": false, 
 "assertion_failure": false, 
 "timeout": false, 
 "dead_code": [], 
 "overflow": false, 
 "money_concurrency": false, 
 "truncation": false
},"StandardToken":{
 "execution_paths": "22", 
 "callstack": false, 
 "reentrancy": false, 
 "modulo": false, 
 "division": false, 
 "execution_time": "3.26779699326", 
 "signedness": false, 
 "evm_code_coverage": "99.9", 
 "underflow": false, 
 "time_dependency": false, 
 "assertion_failure": false, 
 "timeout": false, 
 "dead_code": [
  "STOP "
 ], 
 "overflow": "\n../contractSrc/0x9a7a4ea93ce5a9129d754b7dbeb3a3968939d6b3.sol:StandardToken:46:9\nbalances[_to] += _value\n^\n../contractSrc/0x9a7a4ea93ce5a9129d754b7dbeb3a3968939d6b3.sol:StandardToken:56:9\nbalances[_to] += _value\n^", 
 "money_concurrency": false, 
 "truncation": false
}}