{"ReputationToken":{
 "execution_paths": "41", 
 "callstack": false, 
 "reentrancy": false, 
 "modulo": false, 
 "division": false, 
 "execution_time": "34.459597826", 
 "signedness": false, 
 "evm_code_coverage": "99.9", 
 "underflow": false, 
 "time_dependency": false, 
 "assertion_failure": false, 
 "timeout": false, 
 "dead_code": [
  "STOP "
 ], 
 "overflow": "\n../contractSrc/0xb8d0c280183f274101183d4c0a6057087b43baa8.sol:ReputationToken:153:11\nallSupply+=tokenCount\n^\n../contractSrc/0xb8d0c280183f274101183d4c0a6057087b43baa8.sol:ReputationToken:152:11\nbalances[forAddress]+=tokenCount\n^", 
 "money_concurrency": false, 
 "truncation": false
},"StdToken":{
 "execution_paths": "24", 
 "callstack": false, 
 "reentrancy": false, 
 "modulo": false, 
 "division": false, 
 "execution_time": "1.45610904694", 
 "signedness": false, 
 "evm_code_coverage": "99.9", 
 "underflow": false, 
 "time_dependency": false, 
 "assertion_failure": false, 
 "timeout": false, 
 "dead_code": [
  "STOP "
 ], 
 "overflow": false, 
 "money_concurrency": false, 
 "truncation": false
},"Token":{
 "execution_paths": "14", 
 "callstack": false, 
 "reentrancy": false, 
 "modulo": false, 
 "division": false, 
 "execution_time": "0.178095817566", 
 "signedness": false, 
 "evm_code_coverage": "99.8", 
 "underflow": false, 
 "time_dependency": false, 
 "assertion_failure": false, 
 "timeout": false, 
 "dead_code": [
  "STOP "
 ], 
 "overflow": false, 
 "money_concurrency": false, 
 "truncation": false
}}