{"ANtokContractAirdrop":{
 "execution_paths": "41", 
 "callstack": false, 
 "reentrancy": false, 
 "modulo": false, 
 "division": false, 
 "execution_time": "50.0522880554", 
 "signedness": false, 
 "evm_code_coverage": "71.0", 
 "underflow": false, 
 "time_dependency": false, 
 "assertion_failure": false, 
 "timeout": true, 
 "dead_code": [
  "EXP ", 
  "SWAP1 ", 
  "DIV ", 
  "PUSH20 0xffffffffffffffffffffffffffffffffffffffff ", 
  "AND ", 
  "PUSH20 0xffffffffffffffffffffffffffffffffffffffff ", 
  "AND ", 
  "EQ ", 
  "ISZERO ", 
  "ISZERO ", 
  "PUSH2 0x103a ", 
  "JUMPI ", 
  "PUSH1 0x00 ", 
  "DUP1 ", 
  "REVERT ", 
  "JUMPDEST ", 
  "PUSH1 0x00 ", 
  "PUSH20 0xffffffffffffffffffffffffffffffffffffffff ", 
  "AND ", 
  "DUP2 ", 
  "PUSH20 0xffffffffffffffffffffffffffffffffffffffff ", 
  "AND ", 
  "EQ ", 
  "ISZERO ", 
  "ISZERO ", 
  "ISZERO ", 
  "PUSH2 0x1076 ", 
  "JUMPI ", 
  "PUSH1 0x00 ", 
  "DUP1 ", 
  "REVERT ", 
  "JUMPDEST ", 
  "DUP1 ", 
  "PUSH1 0x03 ", 
  "PUSH1 0x00 ", 
  "PUSH2 0x0100 ", 
  "EXP ", 
  "DUP2 ", 
  "SLOAD ", 
  "DUP2 ", 
  "PUSH20 0xffffffffffffffffffffffffffffffffffffffff ", 
  "MUL ", 
  "NOT ", 
  "AND ", 
  "SWAP1 ", 
  "DUP4 ", 
  "PUSH20 0xffffffffffffffffffffffffffffffffffffffff ", 
  "AND ", 
  "MUL ", 
  "OR ", 
  "SWAP1 ", 
  "SSTORE ", 
  "POP ", 
  "POP ", 
  "JUMP ", 
  "JUMPDEST ", 
  "PUSH1 0x00 ", 
  "DUP2 ", 
  "PUSH1 0x01 ", 
  "PUSH1 0x00 ", 
  "CALLER ", 
  "PUSH20 0xffffffffffffffffffffffffffffffffffffffff ", 
  "DUP1 ", 
  "PUSH4 0xa6f9dae1 ", 
  "EQ ", 
  "PUSH2 0x05af ", 
  "AND ", 
  "PUSH20 0xffffffffffffffffffffffffffffffffffffffff ", 
  "JUMPI ", 
  "DUP1 ", 
  "PUSH4 0xa9059cbb ", 
  "EQ ", 
  "PUSH2 0x05dd ", 
  "JUMPI ", 
  "DUP1 ", 
  "PUSH4 0xdd62ed3e ", 
  "EQ ", 
  "PUSH2 0x0637 ", 
  "AND ", 
  "DUP2 ", 
  "JUMPI ", 
  "DUP1 ", 
  "PUSH4 0xe3dbaff1 ", 
  "ADD ", 
  "SWAP1 ", 
  "DUP2 ", 
  "MSTORE ", 
  "EQ ", 
  "PUSH2 0x06a3 ", 
  "ADD ", 
  "PUSH1 0x00 ", 
  "JUMPI ", 
  "DUP1 ", 
  "PUSH4 0xf49bff7b ", 
  "LT ", 
  "ISZERO ", 
  "ISZERO ", 
  "ISZERO ", 
  "EQ ", 
  "PUSH2 0x06cc ", 
  "JUMPI ", 
  "JUMPI ", 
  "DUP1 ", 
  "REVERT ", 
  "JUMPDEST ", 
  "DUP2 ", 
  "PUSH1 0x01 ", 
  "PUSH1 0x00 ", 
  "CALLER ", 
  "PUSH20 0xffffffffffffffffffffffffffffffffffffffff ", 
  "AND ", 
  "PUSH20 0xffffffffffffffffffffffffffffffffffffffff ", 
  "AND ", 
  "DUP2 ", 
  "MSTORE ", 
  "PUSH1 0x20 ", 
  "ADD ", 
  "SWAP1 ", 
  "DUP2 ", 
  "MSTORE ", 
  "PUSH1 0x20 ", 
  "ADD ", 
  "PUSH1 0x00 ", 
  "SHA3 ", 
  "PUSH1 0x00 ", 
  "DUP3 ", 
  "DUP3 ", 
  "SLOAD ", 
  "SUB ", 
  "SWAP3 ", 
  "POP ", 
  "POP ", 
  "DUP2 ", 
  "SWAP1 ", 
  "SSTORE ", 
  "POP ", 
  "DUP2 ", 
  "PUSH1 0x01 ", 
  "PUSH1 0x00 ", 
  "DUP6 ", 
  "PUSH20 0xffffffffffffffffffffffffffffffffffffffff ", 
  "AND ", 
  "PUSH20 0xffffffffffffffffffffffffffffffffffffffff ", 
  "AND ", 
  "DUP2 ", 
  "MSTORE ", 
  "PUSH1 0x20 ", 
  "ADD ", 
  "SWAP1 ", 
  "DUP2 ", 
  "MSTORE ", 
  "PUSH1 0x20 ", 
  "ADD ", 
  "PUSH1 0x00 ", 
  "SHA3 ", 
  "PUSH1 0x00 ", 
  "DUP3 ", 
  "DUP3 ", 
  "SLOAD ", 
  "ADD ", 
  "SWAP3 ", 
  "POP ", 
  "POP ", 
  "DUP2 ", 
  "SWAP1 ", 
  "SSTORE ", 
  "POP ", 
  "DUP3 ", 
  "PUSH20 0xffffffffffffffffffffffffffffffffffffffff ", 
  "AND ", 
  "CALLER ", 
  "PUSH20 0xffffffffffffffffffffffffffffffffffffffff ", 
  "AND ", 
  "PUSH32 0xddf252ad1be2c89b69c2b068fc378daa952ba7f163c4a11628f55a4df523b3ef ", 
  "DUP5 ", 
  "PUSH1 0x40 ", 
  "PUSH2 0x110a ", 
  "DUP1 ", 
  "DUP3 ", 
  "DUP2 ", 
  "MSTORE ", 
  "PUSH1 0x20 ", 
  "ADD ", 
  "SWAP2 ", 
  "POP ", 
  "POP ", 
  "PUSH1 0x40 ", 
  "MLOAD ", 
  "DUP1 ", 
  "SWAP2 ", 
  "SUB ", 
  "SWAP1 ", 
  "LOG3 ", 
  "PUSH1 0x01 ", 
  "SWAP1 ", 
  "POP ", 
  "SWAP3 ", 
  "SWAP2 ", 
  "POP ", 
  "POP ", 
  "JUMP ", 
  "JUMPDEST ", 
  "PUSH1 0x00 ", 
  "PUSH1 0x02 ", 
  "PUSH1 0x00 ", 
  "DUP5 ", 
  "PUSH20 0xffffffffffffffffffffffffffffffffffffffff ", 
  "AND ", 
  "PUSH20 0xffffffffffffffffffffffffffffffffffffffff ", 
  "AND ", 
  "DUP2 ", 
  "MSTORE ", 
  "PUSH1 0x20 ", 
  "ADD ", 
  "SWAP1 ", 
  "DUP2 ", 
  "MSTORE ", 
  "PUSH1 0x20 ", 
  "ADD ", 
  "PUSH1 0x00 ", 
  "SHA3 ", 
  "PUSH1 0x00 ", 
  "DUP4 ", 
  "PUSH20 0xffffffffffffffffffffffffffffffffffffffff ", 
  "AND ", 
  "PUSH20 0xffffffffffffffffffffffffffffffffffffffff ", 
  "AND ", 
  "DUP2 ", 
  "MSTORE ", 
  "PUSH1 0x20 ", 
  "ADD ", 
  "SWAP1 ", 
  "DUP2 ", 
  "MSTORE ", 
  "PUSH1 0x20 ", 
  "ADD ", 
  "PUSH1 0x00 ", 
  "SHA3 ", 
  "SLOAD ", 
  "SWAP1 ", 
  "POP ", 
  "SWAP3 ", 
  "SWAP2 ", 
  "POP ", 
  "POP ", 
  "JUMP ", 
  "JUMPDEST ", 
  "PUSH1 0x0a ", 
  "SLOAD ", 
  "DUP2 ", 
  "JUMP ", 
  "JUMPDEST ", 
  "PUSH1 0x01 ", 
  "ISZERO ", 
  "ISZERO ", 
  "PUSH1 0x0b ", 
  "PUSH1 0x00 ", 
  "CALLER ", 
  "PUSH20 0xffffffffffffffffffffffffffffffffffffffff ", 
  "AND ", 
  "PUSH20 0xffffffffffffffffffffffffffffffffffffffff ", 
  "AND ", 
  "DUP2 ", 
  "MSTORE ", 
  "PUSH1 0x20 ", 
  "ADD ", 
  "SWAP1 ", 
  "DUP2 ", 
  "MSTORE ", 
  "PUSH1 0x20 ", 
  "ADD ", 
  "PUSH1 0x00 ", 
  "SHA3 ", 
  "PUSH1 0x00 ", 
  "SWAP1 ", 
  "SLOAD ", 
  "SWAP1 ", 
  "PUSH2 0x0100 ", 
  "EXP ", 
  "SWAP1 ", 
  "DIV ", 
  "PUSH1 0xff ", 
  "AND ", 
  "ISZERO ", 
  "ISZERO ", 
  "EQ ", 
  "ISZERO ", 
  "ISZERO ", 
  "ISZERO ", 
  "PUSH2 0x1300 ", 
  "JUMPI ", 
  "PUSH1 0x00 ", 
  "DUP1 ", 
  "REVERT ", 
  "JUMPDEST ", 
  "PUSH1 0x00 ", 
  "PUSH1 0x01 ", 
  "PUSH1 0x00 ", 
  "ADDRESS ", 
  "PUSH20 0xffffffffffffffffffffffffffffffffffffffff ", 
  "AND ", 
  "PUSH20 0xffffffffffffffffffffffffffffffffffffffff ", 
  "AND ", 
  "DUP2 ", 
  "MSTORE ", 
  "PUSH1 0x20 ", 
  "ADD ", 
  "SWAP1 ", 
  "DUP2 ", 
  "MSTORE ", 
  "PUSH1 0x20 ", 
  "ADD ", 
  "PUSH1 0x00 ", 
  "SHA3 ", 
  "SLOAD ", 
  "EQ ", 
  "ISZERO ", 
  "ISZERO ", 
  "ISZERO ", 
  "PUSH2 0x134f ", 
  "JUMPI ", 
  "PUSH1 0x00 ", 
  "DUP1 ", 
  "REVERT ", 
  "JUMPDEST ", 
  "PUSH1 0x01 ", 
  "PUSH1 0x0b ", 
  "PUSH1 0x00 ", 
  "CALLER ", 
  "PUSH20 0xffffffffffffffffffffffffffffffffffffffff ", 
  "AND ", 
  "PUSH20 0xffffffffffffffffffffffffffffffffffffffff ", 
  "AND ", 
  "DUP2 ", 
  "MSTORE ", 
  "PUSH1 0x20 ", 
  "ADD ", 
  "SWAP1 ", 
  "DUP2 ", 
  "MSTORE ", 
  "PUSH1 0x20 ", 
  "ADD ", 
  "PUSH1 0x00 ", 
  "SHA3 ", 
  "PUSH1 0x00 ", 
  "JUMPDEST ", 
  "STOP ", 
  "EXP ", 
  "DUP2 ", 
  "SLOAD ", 
  "DUP2 ", 
  "PUSH1 0xff ", 
  "MUL ", 
  "NOT ", 
  "AND ", 
  "SWAP1 ", 
  "DUP4 ", 
  "ISZERO ", 
  "ISZERO ", 
  "MUL ", 
  "OR ", 
  "SWAP1 ", 
  "SSTORE ", 
  "POP ", 
  "PUSH2 0x13c9 ", 
  "CALLER ", 
  "PUSH1 0x05 ", 
  "PUSH1 0x00 ", 
  "SWAP1 ", 
  "SLOAD ", 
  "SWAP1 ", 
  "PUSH2 0x0100 ", 
  "EXP ", 
  "SWAP1 ", 
  "DIV ", 
  "PUSH1 0xff ", 
  "AND ", 
  "PUSH1 0xff ", 
  "AND ", 
  "PUSH1 0x0a ", 
  "EXP ", 
  "PUSH1 0x01 ", 
  "MUL ", 
  "PUSH2 0x13cb ", 
  "JUMP ", 
  "JUMPDEST ", 
  "JUMP ", 
  "MLOAD ", 
  "ADDRESS ", 
  "PUSH20 0xffffffffffffffffffffffffffffffffffffffff ", 
  "PUSH2 0x0100 ", 
  "AND ", 
  "PUSH4 0xa9059cbb ", 
  "DUP4 ", 
  "DUP4 ", 
  "PUSH1 0x40 ", 
  "MLOAD ", 
  "DUP4 ", 
  "PUSH4 0xffffffff ", 
  "AND ", 
  "PUSH29 0x0100000000000000000000000000000000000000000000000000000000 ", 
  "MUL ", 
  "DUP2 ", 
  "MSTORE ", 
  "PUSH1 0x04 ", 
  "ADD ", 
  "DUP1 ", 
  "DUP4 ", 
  "PUSH20 0xffffffffffffffffffffffffffffffffffffffff ", 
  "JUMPDEST ", 
  "AND ", 
  "PUSH20 0xffffffffffffffffffffffffffffffffffffffff ", 
  "AND ", 
  "DUP2 ", 
  "MSTORE ", 
  "PUSH1 0x20 ", 
  "ADD ", 
  "DUP3 ", 
  "DUP2 ", 
  "MSTORE ", 
  "PUSH1 0x20 ", 
  "ADD ", 
  "SWAP3 ", 
  "POP ", 
  "POP ", 
  "POP ", 
  "PUSH1 0x20 ", 
  "PUSH1 0x40 ", 
  "MLOAD ", 
  "DUP1 ", 
  "DUP4 ", 
  "SUB ", 
  "DUP2 ", 
  "PUSH1 0x00 ", 
  "DUP8 ", 
  "DUP1 ", 
  "EXTCODESIZE ", 
  "ISZERO ", 
  "ISZERO ", 
  "PUSH2 0x146d ", 
  "JUMPI ", 
  "PUSH1 0x00 ", 
  "DUP1 ", 
  "REVERT ", 
  "JUMPDEST ", 
  "GAS ", 
  "CALL ", 
  "ISZERO ", 
  "ISZERO ", 
  "PUSH2 0x147a ", 
  "JUMPI ", 
  "PUSH1 0x00 ", 
  "DUP1 ", 
  "REVERT ", 
  "JUMPDEST ", 
  "POP ", 
  "POP ", 
  "POP ", 
  "PUSH1 0x40 ", 
  "MLOAD ", 
  "DUP1 ", 
  "MLOAD ", 
  "SWAP1 ", 
  "POP ", 
  "POP ", 
  "POP ", 
  "POP ", 
  "JUMP ", 
  "STOP ", 
  "JUMPDEST ", 
  "PUSH1 0x00 ", 
  "SWAP1 ", 
  "POP ", 
  "JUMPDEST ", 
  "DUP2 ", 
  "DUP2 ", 
  "LT ", 
  "ISZERO ", 
  "PUSH2 0x0cf2 ", 
  "JUMPI ", 
  "PUSH2 0x0ce4 ", 
  "DUP4 ", 
  "DUP3 ", 
  "DUP2 ", 
  "MLOAD ", 
  "DUP2 ", 
  "LT ", 
  "ISZERO ", 
  "ISZERO ", 
  "PUSH2 0x0cd2 ", 
  "JUMPI ", 
  "ASSERTFAIL ", 
  "JUMPDEST ", 
  "SWAP1 ", 
  "PUSH1 0x20 ", 
  "ADD ", 
  "SWAP1 ", 
  "PUSH1 0x20 ", 
  "MUL ", 
  "ADD ", 
  "MLOAD ", 
  "PUSH1 0x08 ", 
  "SLOAD ", 
  "PUSH2 0x10ba ", 
  "JUMP ", 
  "JUMPDEST ", 
  "POP ", 
  "DUP1 ", 
  "DUP1 ", 
  "PUSH1 0x01 ", 
  "ADD ", 
  "SWAP2 ", 
  "POP ", 
  "POP ", 
  "PUSH2 0x0cb9 ", 
  "JUMP ", 
  "JUMPDEST ", 
  "PUSH32 0x49144618a873b5cc17bb66841574a039b31eab01fc7fa48808c12f92cb768d43 ", 
  "PUSH1 0x03 ", 
  "PUSH1 0x00 ", 
  "SWAP1 ", 
  "SLOAD ", 
  "SWAP1 ", 
  "PUSH2 0x0100 ", 
  "EXP ", 
  "SWAP1 ", 
  "DIV ", 
  "PUSH20 0xffffffffffffffffffffffffffffffffffffffff ", 
  "PUSH1 0x00 ", 
  "DUP1 ", 
  "REVERT ", 
  "AND ", 
  "PUSH1 0x0a ", 
  "SLOAD ", 
  "TIMESTAMP ", 
  "PUSH1 0x40 ", 
  "MLOAD ", 
  "DUP1 ", 
  "DUP5 ", 
  "PUSH20 0xffffffffffffffffffffffffffffffffffffffff ", 
  "AND ", 
  "PUSH20 0xffffffffffffffffffffffffffffffffffffffff ", 
  "AND ", 
  "DUP2 ", 
  "MSTORE ", 
  "PUSH1 0x20 ", 
  "ADD ", 
  "DUP4 ", 
  "DUP2 ", 
  "MSTORE ", 
  "PUSH1 0x20 ", 
  "ADD ", 
  "DUP3 ", 
  "DUP2 ", 
  "MSTORE ", 
  "PUSH1 0x20 ", 
  "ADD ", 
  "SWAP4 ", 
  "POP ", 
  "POP ", 
  "POP ", 
  "POP ", 
  "PUSH1 0x40 ", 
  "MLOAD ", 
  "DUP1 ", 
  "SWAP2 ", 
  "SUB ", 
  "SWAP1 ", 
  "LOG1 ", 
  "POP ", 
  "POP ", 
  "POP ", 
  "JUMP ", 
  "MSTORE ", 
  "PUSH1 0x20 ", 
  "JUMPDEST ", 
  "PUSH2 0x05db ", 
  "PUSH1 0x04 ", 
  "DUP1 ", 
  "DUP1 ", 
  "CALLDATALOAD ", 
  "PUSH20 0xffffffffffffffffffffffffffffffffffffffff ", 
  "PUSH1 0x20 ", 
  "AND ", 
  "SWAP1 ", 
  "PUSH1 0x20 ", 
  "ADD ", 
  "SWAP1 ", 
  "SWAP2 ", 
  "SWAP1 ", 
  "POP ", 
  "POP ", 
  "PUSH2 0x0fde ", 
  "JUMP ", 
  "JUMPDEST ", 
  "STOP ", 
  "JUMPDEST ", 
  "CALLVALUE ", 
  "ISZERO ", 
  "PUSH2 0x05e8 ", 
  "JUMPI ", 
  "PUSH1 0x00 ", 
  "DUP1 ", 
  "REVERT ", 
  "JUMPDEST ", 
  "PUSH2 0x061d ", 
  "PUSH1 0x04 ", 
  "DUP1 ", 
  "DUP1 ", 
  "CALLDATALOAD ", 
  "PUSH20 0xffffffffffffffffffffffffffffffffffffffff ", 
  "AND ", 
  "SWAP1 ", 
  "PUSH1 0x20 ", 
  "ADD ", 
  "SWAP1 ", 
  "SWAP2 ", 
  "SWAP1 ", 
  "DUP1 ", 
  "CALLDATALOAD ", 
  "SWAP1 ", 
  "PUSH1 0x20 ", 
  "ADD ", 
  "SWAP1 ", 
  "SWAP2 ", 
  "SWAP1 ", 
  "POP ", 
  "POP ", 
  "PUSH2 0x10ba ", 
  "JUMP ", 
  "JUMPDEST ", 
  "PUSH1 0x40 ", 
  "MLOAD ", 
  "DUP1 ", 
  "DUP3 ", 
  "ISZERO ", 
  "ISZERO ", 
  "ISZERO ", 
  "ISZERO ", 
  "DUP2 ", 
  "MSTORE ", 
  "PUSH1 0x20 ", 
  "ADD ", 
  "SWAP2 ", 
  "POP ", 
  "POP ", 
  "PUSH1 0x40 ", 
  "MLOAD ", 
  "DUP1 ", 
  "SWAP2 ", 
  "SUB ", 
  "SWAP1 ", 
  "RETURN ", 
  "JUMPDEST ", 
  "CALLVALUE ", 
  "ISZERO ", 
  "PUSH2 0x0642 ", 
  "JUMPI ", 
  "PUSH1 0x00 ", 
  "DUP1 ", 
  "REVERT ", 
  "JUMPDEST ", 
  "PUSH2 0x068d ", 
  "PUSH1 0x04 ", 
  "DUP1 ", 
  "DUP1 ", 
  "CALLDATALOAD ", 
  "PUSH20 0xffffffffffffffffffffffffffffffffffffffff ", 
  "AND ", 
  "SWAP1 ", 
  "PUSH1 0x20 ", 
  "ADD ", 
  "SWAP1 ", 
  "SWAP2 ", 
  "SWAP1 ", 
  "DUP1 ", 
  "CALLDATALOAD ", 
  "PUSH20 0xffffffffffffffffffffffffffffffffffffffff ", 
  "SHA3 ", 
  "AND ", 
  "SWAP1 ", 
  "PUSH1 0x20 ", 
  "ADD ", 
  "SWAP1 ", 
  "SWAP2 ", 
  "SWAP1 ", 
  "POP ", 
  "POP ", 
  "PUSH2 0x1213 ", 
  "JUMP ", 
  "JUMPDEST ", 
  "PUSH1 0x40 ", 
  "MLOAD ", 
  "DUP1 ", 
  "DUP3 ", 
  "DUP2 ", 
  "MSTORE ", 
  "PUSH1 0x20 ", 
  "ADD ", 
  "SWAP2 ", 
  "POP ", 
  "POP ", 
  "PUSH1 0x40 ", 
  "MLOAD ", 
  "DUP1 ", 
  "SWAP2 ", 
  "SUB ", 
  "SWAP1 ", 
  "RETURN ", 
  "JUMPDEST ", 
  "CALLVALUE ", 
  "ISZERO ", 
  "PUSH2 0x06ae ", 
  "JUMPI ", 
  "PUSH1 0x00 ", 
  "DUP1 ", 
  "REVERT ", 
  "JUMPDEST ", 
  "PUSH2 0x06b6 ", 
  "PUSH2 0x129a ", 
  "JUMP ", 
  "JUMPDEST ", 
  "PUSH1 0x40 ", 
  "MLOAD ", 
  "DUP1 ", 
  "DUP3 ", 
  "DUP2 ", 
  "MSTORE ", 
  "PUSH1 0x20 ", 
  "ADD ", 
  "SWAP2 ", 
  "POP ", 
  "POP ", 
  "PUSH1 0x40 ", 
  "MLOAD ", 
  "DUP1 ", 
  "SWAP2 ", 
  "SUB ", 
  "SWAP1 ", 
  "RETURN ", 
  "JUMPDEST ", 
  "PUSH2 0x06d4 ", 
  "PUSH2 0x12a0 ", 
  "JUMP ", 
  "JUMPDEST ", 
  "STOP ", 
  "SLOAD ", 
  "PUSH1 0x00 ", 
  "PUSH2 0x0100 ", 
  "DUP1 ", 
  "DUP4 ", 
  "SLOAD ", 
  "DIV ", 
  "MUL ", 
  "DUP4 ", 
  "MSTORE ", 
  "SWAP2 ", 
  "PUSH1 0x20 ", 
  "ADD ", 
  "SWAP2 ", 
  "PUSH2 0x0fd6 ", 
  "JUMP ", 
  "JUMPDEST ", 
  "CALLER ", 
  "PUSH20 0xffffffffffffffffffffffffffffffffffffffff ", 
  "AND ", 
  "PUSH1 0x03 ", 
  "PUSH1 0x00 ", 
  "SWAP1 ", 
  "SLOAD ", 
  "SWAP1 ", 
  "PUSH2 0x0100 "
 ], 
 "overflow": "\n../contractSrc/0x15e4cf1950ffa338ce5bc59456b3e579ed1bead3.sol:ANtokContractAirdrop:132:16\npaySize * count\n^\n../contractSrc/0x15e4cf1950ffa338ce5bc59456b3e579ed1bead3.sol:ANtokContractAirdrop:68:9\nbalances[_to] += _value\n^", 
 "money_concurrency": false, 
 "truncation": false
},"ERC20":{
 "execution_paths": "18", 
 "callstack": false, 
 "reentrancy": false, 
 "modulo": false, 
 "division": false, 
 "execution_time": "2.32246994972", 
 "signedness": false, 
 "evm_code_coverage": "99.9", 
 "underflow": false, 
 "time_dependency": false, 
 "assertion_failure": false, 
 "timeout": false, 
 "dead_code": [
  "STOP "
 ], 
 "overflow": "\n../contractSrc/0x15e4cf1950ffa338ce5bc59456b3e579ed1bead3.sol:ERC20:58:9\nbalances[_to] += _value\n^\n../contractSrc/0x15e4cf1950ffa338ce5bc59456b3e579ed1bead3.sol:ERC20:68:9\nbalances[_to] += _value\n^", 
 "money_concurrency": false, 
 "truncation": false
},"OwnableToken":{
 "execution_paths": "5", 
 "callstack": false, 
 "reentrancy": false, 
 "modulo": false, 
 "division": false, 
 "execution_time": "0.154122114182", 
 "signedness": false, 
 "evm_code_coverage": "99.1", 
 "underflow": false, 
 "time_dependency": false, 
 "assertion_failure": false, 
 "timeout": false, 
 "dead_code": [
  "STOP "
 ], 
 "overflow": false, 
 "money_concurrency": false, 
 "truncation": false
}}