{"Haltable":{
 "execution_paths": "17", 
 "callstack": false, 
 "reentrancy": false, 
 "modulo": false, 
 "division": false, 
 "execution_time": "0.207328081131", 
 "signedness": false, 
 "evm_code_coverage": "99.7", 
 "underflow": false, 
 "time_dependency": false, 
 "assertion_failure": false, 
 "timeout": false, 
 "dead_code": [
  "STOP "
 ], 
 "overflow": false, 
 "money_concurrency": false, 
 "truncation": false
},"MintableToken":{
 "execution_paths": "49", 
 "callstack": false, 
 "reentrancy": false, 
 "modulo": false, 
 "division": false, 
 "execution_time": "1.58578801155", 
 "signedness": false, 
 "evm_code_coverage": "99.9", 
 "underflow": false, 
 "time_dependency": false, 
 "assertion_failure": false, 
 "timeout": false, 
 "dead_code": [
  "STOP "
 ], 
 "overflow": false, 
 "money_concurrency": false, 
 "truncation": false
},"MintedTokenCappedCrowdsale":{
 "execution_paths": "276", 
 "callstack": false, 
 "reentrancy": false, 
 "modulo": false, 
 "division": false, 
 "execution_time": "41.9668171406", 
 "signedness": false, 
 "evm_code_coverage": "83.9", 
 "underflow": false, 
 "time_dependency": "\n../contractSrc/0xa5ca78d849fa2b1cd4f37e81e99f6c5cc6c92a7e.sol:MintedTokenCappedCrowdsale:663:10\nif (block.timestamp < startsAt) return State.PreFunding;\r\n^", 
 "assertion_failure": false, 
 "timeout": false, 
 "dead_code": [
  "JUMPDEST ", 
  "STOP ", 
  "CALLER ", 
  "PUSH20 0xffffffffffffffffffffffffffffffffffffffff ", 
  "PUSH2 0x2160 ", 
  "SWAP2 ", 
  "AND ", 
  "EQ ", 
  "ISZERO ", 
  "ISZERO ", 
  "PUSH2 0x282c ", 
  "JUMPI ", 
  "PUSH1 0x00 ", 
  "DUP1 ", 
  "REVERT ", 
  "JUMPDEST ", 
  "PUSH1 0x01 ", 
  "SLOAD ", 
  "PUSH1 0x0b ", 
  "SLOAD ", 
  "GT ", 
  "ISZERO ", 
  "PUSH2 0x283d ", 
  "AND ", 
  "JUMPI ", 
  "PUSH1 0x00 ", 
  "DUP1 ", 
  "REVERT ", 
  "JUMPDEST ", 
  "DUP1 ", 
  "PUSH1 0x05 ", 
  "PUSH1 0x00 ", 
  "PUSH2 0x0100 ", 
  "EXP ", 
  "DUP2 ", 
  "SLOAD ", 
  "DUP2 ", 
  "PUSH20 0xffffffffffffffffffffffffffffffffffffffff ", 
  "ISZERO ", 
  "PUSH2 0x216d ", 
  "NOT ", 
  "AND ", 
  "SWAP1 ", 
  "DUP4 ", 
  "PUSH20 0xffffffffffffffffffffffffffffffffffffffff ", 
  "NOT ", 
  "PUSH1 0x0c ", 
  "JUMPI ", 
  "AND ", 
  "SWAP2 ", 
  "OR ", 
  "SWAP1 ", 
  "SSTORE ", 
  "POP ", 
  "POP ", 
  "JUMP ", 
  "JUMPDEST ", 
  "SWAP1 ", 
  "DUP1 ", 
  "AND ", 
  "PUSH1 0x0f ", 
  "PUSH2 0x288e ", 
  "DUP6 ", 
  "DUP6 ", 
  "REVERT ", 
  "PUSH2 0x1238 ", 
  "JUMP ", 
  "JUMPDEST ", 
  "POP ", 
  "POP ", 
  "POP ", 
  "POP ", 
  "JUMP ", 
  "MLOAD ", 
  "POP ", 
  "PUSH1 0x00 ", 
  "DUP5 ", 
  "SWAP1 ", 
  "SLOAD ", 
  "POP ", 
  "PUSH2 0x0100 ", 
  "EXP ", 
  "SWAP1 ", 
  "POP ", 
  "SWAP1 ", 
  "PUSH1 0x40 ", 
  "MLOAD ", 
  "PUSH1 0x40 ", 
  "AND ", 
  "DUP2 ", 
  "JUMP ", 
  "MLOAD ", 
  "JUMPDEST ", 
  "PUSH1 0x07 ", 
  "DUP2 ", 
  "GT ", 
  "ISZERO ", 
  "PUSH2 0x20d0 ", 
  "JUMPI ", 
  "ASSERTFAIL ", 
  "JUMPDEST ", 
  "EQ ", 
  "ISZERO ", 
  "ISZERO ", 
  "PUSH2 0x20dc ", 
  "JUMPI ", 
  "PUSH1 0x00 ", 
  "DUP1 ", 
  "REVERT ", 
  "JUMPDEST ", 
  "PUSH1 0x00 ", 
  "CALLVALUE ", 
  "EQ ", 
  "ISZERO ", 
  "PUSH2 0x20ea ", 
  "SWAP1 ", 
  "JUMPI ", 
  "PUSH1 0x00 ", 
  "DUP1 ", 
  "REVERT ", 
  "JUMPDEST ", 
  "PUSH1 0x0c ", 
  "SLOAD ", 
  "PUSH20 0x0000000000000000000000000000000000000001 ", 
  "POP ", 
  "POP ", 
  "JUMPDEST ", 
  "PUSH1 0x07 ", 
  "DUP2 ", 
  "GT ", 
  "ISZERO ", 
  "PUSH2 0x1909 ", 
  "JUMPI ", 
  "ASSERTFAIL ", 
  "JUMPDEST ", 
  "EQ ", 
  "ISZERO ", 
  "ISZERO ", 
  "PUSH2 0x1915 ", 
  "DUP4 ", 
  "PUSH4 0xffffffff ", 
  "JUMPI ", 
  "PUSH1 0x00 ", 
  "DUP1 ", 
  "REVERT ", 
  "JUMPDEST ", 
  "PUSH1 0x00 ", 
  "DUP1 ", 
  "SWAP1 ", 
  "SLOAD ", 
  "SWAP1 ", 
  "PUSH2 0x0100 ", 
  "DIV ", 
  "EXP ", 
  "SWAP1 ", 
  "DIV ", 
  "PUSH20 0xffffffffffffffffffffffffffffffffffffffff ", 
  "PUSH4 0xffffffff ", 
  "MUL ", 
  "DUP2 ", 
  "MSTORE ", 
  "PUSH1 0x04 ", 
  "AND ", 
  "PUSH20 0xffffffffffffffffffffffffffffffffffffffff ", 
  "DUP1 ", 
  "DUP2 ", 
  "DUP2 ", 
  "MSTORE ", 
  "PUSH1 0x20 ", 
  "ADD ", 
  "DUP3 ", 
  "DUP2 ", 
  "MSTORE ", 
  "PUSH1 0x20 ", 
  "ADD ", 
  "SWAP3 ", 
  "POP ", 
  "POP ", 
  "POP ", 
  "PUSH1 0x20 ", 
  "JUMPDEST ", 
  "STOP ", 
  "CALLER ", 
  "PUSH20 0xffffffffffffffffffffffffffffffffffffffff ", 
  "DUP4 ", 
  "SUB ", 
  "DUP2 ", 
  "DUP7 ", 
  "DUP1 ", 
  "EXTCODESIZE ", 
  "ISZERO ", 
  "ISZERO ", 
  "MSTORE ", 
  "JUMPI ", 
  "PUSH1 0x00 ", 
  "DUP1 ", 
  "REVERT ", 
  "JUMPDEST ", 
  "GAS ", 
  "DELEGATECALL ", 
  "ISZERO ", 
  "AND ", 
  "EQ ", 
  "ISZERO ", 
  "ISZERO ", 
  "PUSH2 0x1970 ", 
  "PUSH1 0x00 ", 
  "JUMPI ", 
  "PUSH1 0x00 ", 
  "JUMPDEST ", 
  "DUP1 ", 
  "REVERT ", 
  "JUMPDEST ", 
  "PUSH1 0x00 ", 
  "PUSH1 0x14 ", 
  "DUP1 ", 
  "SWAP1 ", 
  "SLOAD ", 
  "SWAP1 ", 
  "PUSH2 0x0100 ", 
  "PUSH1 0x20 ", 
  "DUP2 ", 
  "EXP ", 
  "SWAP1 ", 
  "DIV ", 
  "PUSH1 0xff ", 
  "JUMP ", 
  "AND ", 
  "ISZERO ", 
  "PUSH2 0x198a ", 
  "JUMPI ", 
  "PUSH1 0x00 ", 
  "DUP1 ", 
  "REVERT ", 
  "JUMPDEST ", 
  "PUSH1 0x0e ", 
  "PUSH1 0x00 ", 
  "SWAP1 ", 
  "SLOAD ", 
  "SWAP1 ", 
  "PUSH2 0x0100 ", 
  "EXP ", 
  "SWAP1 ", 
  "DIV ", 
  "PUSH1 0xff ", 
  "AND ", 
  "ISZERO ", 
  "PUSH2 0x19a4 ", 
  "JUMPDEST ", 
  "JUMPI ", 
  "PUSH1 0x00 ", 
  "DUP1 ", 
  "REVERT ", 
  "JUMPDEST ", 
  "PUSH1 0x00 ", 
  "PUSH1 0x04 ", 
  "PUSH1 0x00 ", 
  "SWAP1 ", 
  "SLOAD ", 
  "SWAP1 ", 
  "PUSH2 0x0100 ", 
  "EXP ", 
  "SWAP1 ", 
  "DIV ", 
  "PUSH20 0xffffffffffffffffffffffffffffffffffffffff ", 
  "PUSH1 0x02 ", 
  "PUSH1 0x20 ", 
  "PUSH2 0x0100 ", 
  "ADD ", 
  "AND ", 
  "PUSH20 0xffffffffffffffffffffffffffffffffffffffff ", 
  "EXP ", 
  "MSTORE ", 
  "DUP2 ", 
  "PUSH1 0x20 ", 
  "POP ", 
  "AND ", 
  "EQ ", 
  "ISZERO ", 
  "ISZERO ", 
  "PUSH2 0x1a7c ", 
  "DUP2 ", 
  "DUP2 ", 
  "JUMPI ", 
  "PUSH1 0x04 ", 
  "PUSH1 0x00 ", 
  "SWAP1 ", 
  "SLOAD ", 
  "SWAP1 ", 
  "PUSH2 0x0100 ", 
  "EXP ", 
  "SWAP1 ", 
  "DIV ", 
  "PUSH20 0xffffffffffffffffffffffffffffffffffffffff ", 
  "MUL ", 
  "SHA3 ", 
  "NOT ", 
  "JUMPDEST ", 
  "PUSH20 0xffffffffffffffffffffffffffffffffffffffff ", 
  "JUMPI ", 
  "STOP ", 
  "STOP ", 
  "PUSH2 0x0100 ", 
  "DUP3 ", 
  "AND ", 
  "PUSH4 0x0bf318a3 ", 
  "EQ ", 
  "PUSH1 0x40 ", 
  "MLOAD ", 
  "DUP2 ", 
  "PUSH4 0xffffffff ", 
  "AND ", 
  "PUSH29 0x0100000000000000000000000000000000000000000000000000000000 ", 
  "SSTORE ", 
  "PUSH20 0xffffffffffffffffffffffffffffffffffffffff ", 
  "MUL ", 
  "JUMPI ", 
  "MUL ", 
  "DUP2 ", 
  "MSTORE ", 
  "PUSH1 0x04 ", 
  "ADD ", 
  "PUSH1 0x00 ", 
  "JUMP ", 
  "PUSH1 0x40 ", 
  "MLOAD ", 
  "DUP1 ", 
  "DUP4 ", 
  "SUB ", 
  "DUP2 ", 
  "DUP1 ", 
  "PUSH4 0xf4869726 ", 
  "DUP8 ", 
  "DUP1 ", 
  "EXTCODESIZE ", 
  "ISZERO ", 
  "EQ ", 
  "PUSH2 0x1a6b ", 
  "STOP ", 
  "JUMPI ", 
  "DUP1 ", 
  "PUSH4 0xfc0c546a ", 
  "DUP1 ", 
  "REVERT ", 
  "JUMPDEST ", 
  "GAS ", 
  "EQ ", 
  "PUSH2 0x0cda ", 
  "ISZERO ", 
  "PUSH2 0x1a78 ", 
  "JUMPI ", 
  "JUMPI ", 
  "PUSH1 0x00 ", 
  "DUP1 ", 
  "REVERT ", 
  "JUMPDEST ", 
  "POP ", 
  "POP ", 
  "POP ", 
  "JUMPDEST ", 
  "PUSH1 0x01 ", 
  "PUSH1 0x0e ", 
  "PUSH1 0x00 ", 
  "PUSH2 0x0100 ", 
  "PUSH1 0x00 ", 
  "EXP ", 
  "DUP2 ", 
  "SLOAD ", 
  "DUP2 ", 
  "PUSH1 0xff ", 
  "MUL ", 
  "NOT ", 
  "AND ", 
  "SWAP1 ", 
  "DUP4 ", 
  "ISZERO ", 
  "ISZERO ", 
  "MUL ", 
  "OR ", 
  "SWAP1 ", 
  "SSTORE ", 
  "POP ", 
  "POP ", 
  "JUMP ", 
  "PUSH1 0x20 ", 
  "PUSH1 0xff ", 
  "MUL ", 
  "EXP ", 
  "MUL ", 
  "DUP9 ", 
  "AND ", 
  "PUSH2 0x1c65 ", 
  "CALL ", 
  "PUSH20 0xffffffffffffffffffffffffffffffffffffffff ", 
  "SWAP4 ", 
  "POP ", 
  "DUP4 ", 
  "CALLER ", 
  "PUSH20 0xffffffffffffffffffffffffffffffffffffffff ", 
  "DUP6 ", 
  "DUP6 ", 
  "PUSH1 0x00 ", 
  "JUMPDEST ", 
  "PUSH1 0x02 ", 
  "JUMPDEST ", 
  "STOP ", 
  "SWAP1 ", 
  "JUMPDEST ", 
  "POP ", 
  "POP ", 
  "POP ", 
  "POP ", 
  "POP ", 
  "POP ", 
  "JUMP ", 
  "ISZERO ", 
  "SWAP1 ", 
  "PUSH1 0x20 ", 
  "JUMPDEST ", 
  "STOP ", 
  "PUSH1 0x00 ", 
  "SHA3 ", 
  "PUSH1 0x00 ", 
  "SWAP1 ", 
  "SSTORE ", 
  "POP ", 
  "JUMPDEST ", 
  "PUSH1 0x07 ", 
  "DUP2 ", 
  "GT ", 
  "ISZERO ", 
  "PUSH2 0x1c09 ", 
  "ADD ", 
  "JUMPI ", 
  "ASSERTFAIL ", 
  "JUMPDEST ", 
  "EQ ", 
  "ISZERO ", 
  "ISZERO ", 
  "PUSH2 0x1c15 ", 
  "SLOAD ", 
  "JUMPI ", 
  "PUSH1 0x00 ", 
  "DUP1 ", 
  "REVERT ", 
  "JUMPDEST ", 
  "JUMPDEST ", 
  "STOP ", 
  "PUSH1 0x00 ", 
  "CALLER ", 
  "PUSH20 0xffffffffffffffffffffffffffffffffffffffff ", 
  "PUSH1 0x00 ", 
  "DUP1 ", 
  "REVERT ", 
  "JUMPDEST ", 
  "PUSH2 0x0c4f ", 
  "PUSH1 0x04 ", 
  "DUP1 ", 
  "DUP1 ", 
  "CALLDATALOAD ", 
  "PUSH20 0xffffffffffffffffffffffffffffffffffffffff ", 
  "AND ", 
  "PUSH20 0xffffffffffffffffffffffffffffffffffffffff ", 
  "AND ", 
  "SWAP1 ", 
  "AND ", 
  "SWAP1 ", 
  "PUSH1 0x20 ", 
  "ADD ", 
  "SWAP1 ", 
  "SWAP2 ", 
  "SWAP1 ", 
  "POP ", 
  "POP ", 
  "PUSH2 0x26fc ", 
  "SWAP1 ", 
  "DUP2 ", 
  "JUMP ", 
  "JUMPDEST ", 
  "STOP ", 
  "JUMPDEST ", 
  "CALLVALUE ", 
  "ISZERO ", 
  "PUSH2 0x0c5c ", 
  "SLOAD ", 
  "SWAP2 ", 
  "JUMPDEST ", 
  "PUSH1 0x00 ", 
  "DUP1 ", 
  "REVERT ", 
  "JUMPDEST ", 
  "PUSH2 0x0c88 ", 
  "PUSH1 0x04 ", 
  "PUSH1 0x00 ", 
  "DUP1 ", 
  "DUP1 ", 
  "CALLDATALOAD ", 
  "PUSH20 0xffffffffffffffffffffffffffffffffffffffff ", 
  "PUSH1 0x00 ", 
  "PUSH1 0x0f ", 
  "PUSH1 0x00 ", 
  "CALLER ", 
  "PUSH20 0xffffffffffffffffffffffffffffffffffffffff ", 
  "AND ", 
  "SWAP1 ", 
  "PUSH1 0x20 ", 
  "ADD ", 
  "SWAP1 ", 
  "SWAP2 ", 
  "SWAP1 ", 
  "POP ", 
  "POP ", 
  "PUSH2 0x27d1 ", 
  "JUMP ", 
  "JUMPDEST ", 
  "STOP ", 
  "JUMPDEST ", 
  "PUSH2 0x0cd8 ", 
  "PUSH1 0x04 ", 
  "DUP1 ", 
  "DUP1 ", 
  "CALLDATALOAD ", 
  "PUSH16 0xffffffffffffffffffffffffffffffff ", 
  "AND ", 
  "DUP2 ", 
  "MSTORE ", 
  "PUSH1 0x20 ", 
  "SSTORE ", 
  "ADD ", 
  "SWAP1 ", 
  "DUP2 ", 
  "MSTORE ", 
  "REVERT ", 
  "ADD ", 
  "AND ", 
  "SWAP1 ", 
  "PUSH1 0x20 ", 
  "DUP2 ", 
  "ADD ", 
  "SWAP1 ", 
  "SWAP2 ", 
  "SWAP1 ", 
  "DUP1 ", 
  "CALLDATALOAD ", 
  "PUSH1 0xff ", 
  "AND ", 
  "SWAP1 ", 
  "PUSH1 0x20 ", 
  "ADD ", 
  "SWAP1 ", 
  "SWAP2 ", 
  "SWAP1 ", 
  "DUP1 ", 
  "CALLDATALOAD ", 
  "PUSH1 0x00 ", 
  "NOT ", 
  "AND ", 
  "SWAP1 ", 
  "PUSH1 0x20 ", 
  "ADD ", 
  "SWAP1 ", 
  "SWAP2 ", 
  "SWAP1 ", 
  "DUP1 ", 
  "CALLDATALOAD ", 
  "PUSH1 0x00 ", 
  "SWAP1 ", 
  "NOT ", 
  "AND ", 
  "SWAP1 ", 
  "PUSH1 0x20 ", 
  "MLOAD ", 
  "ADD ", 
  "SWAP1 ", 
  "SWAP2 ", 
  "SWAP1 ", 
  "POP ", 
  "POP ", 
  "PUSH2 0x2881 ", 
  "DUP4 ", 
  "JUMP ", 
  "JUMPDEST ", 
  "STOP ", 
  "JUMPDEST ", 
  "CALLVALUE ", 
  "ISZERO ", 
  "PUSH2 0x0ce5 ", 
  "JUMPI ", 
  "PUSH1 0x00 ", 
  "DUP1 ", 
  "REVERT ", 
  "JUMPDEST ", 
  "PUSH2 0x0ced ", 
  "PUSH2 0x2894 ", 
  "JUMP ", 
  "JUMPDEST ", 
  "PUSH1 0x40 ", 
  "MLOAD ", 
  "DUP1 ", 
  "DUP3 ", 
  "PUSH20 0xffffffffffffffffffffffffffffffffffffffff ", 
  "DUP2 ", 
  "PUSH1 0x0d ", 
  "PUSH1 0x04 ", 
  "PUSH1 0x02 ", 
  "ADD ", 
  "AND ", 
  "DUP4 ", 
  "DUP2 ", 
  "MSTORE ", 
  "PUSH1 0x20 ", 
  "PUSH29 0x0100000000000000000000000000000000000000000000000000000000 ", 
  "DUP3 ", 
  "DUP2 ", 
  "MSTORE ", 
  "PUSH1 0x20 ", 
  "ADD ", 
  "SWAP3 ", 
  "POP ", 
  "AND ", 
  "PUSH20 0xffffffffffffffffffffffffffffffffffffffff ", 
  "PUSH1 0x20 ", 
  "PUSH1 0x40 ", 
  "MLOAD ", 
  "DUP1 ", 
  "DUP4 ", 
  "SUB ", 
  "DUP2 ", 
  "DUP7 ", 
  "DUP1 ", 
  "EXTCODESIZE ", 
  "ISZERO ", 
  "ISZERO ", 
  "PUSH2 0x1d20 ", 
  "JUMPI ", 
  "PUSH1 0x00 ", 
  "AND ", 
  "DUP2 ", 
  "MSTORE ", 
  "PUSH1 0x20 ", 
  "DELEGATECALL ", 
  "ADD ", 
  "SWAP2 ", 
  "POP ", 
  "POP ", 
  "PUSH1 0x40 ", 
  "JUMPI ", 
  "MLOAD ", 
  "DUP1 ", 
  "SWAP2 ", 
  "SUB ", 
  "SWAP1 ", 
  "RETURN ", 
  "POP ", 
  "POP ", 
  "PUSH1 0x40 ", 
  "MLOAD ", 
  "DUP1 ", 
  "MLOAD ", 
  "SWAP1 ", 
  "POP ", 
  "PUSH1 0x0d ", 
  "DUP2 ", 
  "SWAP1 ", 
  "SSTORE ", 
  "POP ", 
  "PUSH32 0xbb28353e4598c3b9199101a66e0989549b659a59a54d2c27fbb183f1932c8e6d ", 
  "PUSH1 0x0e ", 
  "PUSH20 0x0000000000000000000000000000000000000001 ", 
  "AND ", 
  "CALLER ", 
  "DUP4 ", 
  "PUSH1 0x40 ", 
  "MLOAD ", 
  "DUP1 ", 
  "DUP4 ", 
  "PUSH20 0xffffffffffffffffffffffffffffffffffffffff ", 
  "PUSH20 0xffffffffffffffffffffffffffffffffffffffff ", 
  "SWAP1 ", 
  "POP ", 
  "AND ", 
  "PUSH20 0xffffffffffffffffffffffffffffffffffffffff ", 
  "AND ", 
  "DUP2 ", 
  "MSTORE ", 
  "AND ", 
  "SLOAD ", 
  "ADD ", 
  "DUP3 ", 
  "DUP2 ", 
  "MSTORE ", 
  "PUSH1 0x20 ", 
  "DUP2 ", 
  "ADD ", 
  "SWAP3 ", 
  "POP ", 
  "POP ", 
  "POP ", 
  "PUSH1 0x40 ", 
  "MLOAD ", 
  "DUP1 ", 
  "SWAP2 ", 
  "SUB ", 
  "SWAP1 ", 
  "LOG1 ", 
  "CALLER ", 
  "PUSH20 0xffffffffffffffffffffffffffffffffffffffff ", 
  "AND ", 
  "SWAP1 ", 
  "DUP4 ", 
  "ISZERO ", 
  "ISZERO ", 
  "MUL ", 
  "OR ", 
  "SWAP1 ", 
  "MUL ", 
  "POP ", 
  "DUP1 ", 
  "PUSH1 0x0e ", 
  "PUSH1 0x03 ", 
  "PUSH2 0x0100 ", 
  "EXP ", 
  "DUP2 ", 
  "MSTORE ", 
  "PUSH2 0x08fc ", 
  "PUSH20 0xffffffffffffffffffffffffffffffffffffffff ", 
  "DUP4 ", 
  "SWAP1 ", 
  "DUP2 ", 
  "ISZERO ", 
  "MUL ", 
  "SWAP1 ", 
  "PUSH1 0x40 ", 
  "MLOAD ", 
  "PUSH1 0x00 ", 
  "PUSH1 0x40 ", 
  "MLOAD ", 
  "DUP1 ", 
  "DUP4 ", 
  "SUB ", 
  "DUP2 ", 
  "DUP6 ", 
  "DUP9 ", 
  "DUP1 ", 
  "JUMPDEST ", 
  "STOP ", 
  "POP ", 
  "POP ", 
  "POP ", 
  "POP ", 
  "ISZERO ", 
  "ISZERO ", 
  "PUSH2 0x1de8 ", 
  "JUMPI ", 
  "PUSH1 0x00 ", 
  "DUP1 ", 
  "REVERT ", 
  "JUMPDEST ", 
  "POP ", 
  "POP ", 
  "JUMP ", 
  "JUMPDEST ", 
  "AND ", 
  "MUL ", 
  "OR ", 
  "POP ", 
  "SSTORE ", 
  "POP ", 
  "PUSH32 0x48d826081348f5f00e8a33c9ae8ce89ed4c6e88400b585a478bc203d9e8177d3 ", 
  "ADD ", 
  "PUSH4 0x66098d4f ", 
  "PUSH1 0x0e ", 
  "PUSH1 0x01 ", 
  "SWAP1 ", 
  "SLOAD ", 
  "SWAP1 ", 
  "PUSH2 0x0100 ", 
  "EXP ", 
  "SWAP1 ", 
  "DIV ", 
  "PUSH1 0xff ", 
  "AND ", 
  "PUSH1 0x0e ", 
  "PUSH1 0x00 ", 
  "SWAP1 ", 
  "SLOAD ", 
  "SWAP1 ", 
  "PUSH2 0x0100 ", 
  "POP ", 
  "SWAP1 ", 
  "DIV ", 
  "PUSH1 0xff ", 
  "AND ", 
  "POP ", 
  "PUSH1 0x03 ", 
  "SWAP1 ", 
  "SLOAD ", 
  "CALLVALUE ", 
  "PUSH2 0x0100 ", 
  "EXP ", 
  "SWAP1 ", 
  "PUSH1 0x40 ", 
  "PUSH20 0xffffffffffffffffffffffffffffffffffffffff ", 
  "ISZERO ", 
  "JUMPDEST ", 
  "STOP ", 
  "PUSH2 0x0c8a ", 
  "AND ", 
  "PUSH1 0x40 ", 
  "MLOAD ", 
  "DUP1 ", 
  "DUP5 ", 
  "ISZERO ", 
  "ISZERO ", 
  "ISZERO ", 
  "ISZERO ", 
  "DUP2 ", 
  "MSTORE ", 
  "JUMPI ", 
  "ADD ", 
  "DUP4 ", 
  "ISZERO ", 
  "ISZERO ", 
  "PUSH1 0x00 ", 
  "ISZERO ", 
  "DUP2 ", 
  "MSTORE ", 
  "PUSH1 0x20 ", 
  "ADD ", 
  "DUP3 ", 
  "PUSH20 0xffffffffffffffffffffffffffffffffffffffff ", 
  "AND ", 
  "PUSH29 0x0100000000000000000000000000000000000000000000000000000000 ", 
  "ISZERO ", 
  "AND ", 
  "PUSH20 0xffffffffffffffffffffffffffffffffffffffff ", 
  "CALL ", 
  "ISZERO ", 
  "DUP1 ", 
  "JUMPDEST ", 
  "AND ", 
  "DUP2 ", 
  "MSTORE ", 
  "JUMP ", 
  "ADD ", 
  "SWAP4 ", 
  "POP ", 
  "POP ", 
  "POP ", 
  "POP ", 
  "PUSH1 0x40 ", 
  "MLOAD ", 
  "DUP1 ", 
  "SWAP2 ", 
  "SUB ", 
  "SWAP1 ", 
  "LOG1 ", 
  "POP ", 
  "POP ", 
  "JUMP ", 
  "DUP1 ", 
  "MUL ", 
  "REVERT ", 
  "JUMPDEST ", 
  "GAS ", 
  "ISZERO ", 
  "ISZERO ", 
  "POP ", 
  "PUSH2 0x1d2d ", 
  "DIV ", 
  "PUSH1 0x00 ", 
  "JUMPDEST ", 
  "POP ", 
  "DUP1 ", 
  "JUMP ", 
  "JUMPDEST ", 
  "PUSH1 0x00 ", 
  "DUP1 ", 
  "SWAP1 ", 
  "SLOAD ", 
  "SWAP1 ", 
  "DUP1 ", 
  "EXP ", 
  "SWAP1 ", 
  "DIV ", 
  "REVERT ", 
  "JUMPDEST ", 
  "POP ", 
  "AND ", 
  "PUSH20 0xffffffffffffffffffffffffffffffffffffffff ", 
  "EXP ", 
  "AND ", 
  "CALLER ", 
  "PUSH20 0xffffffffffffffffffffffffffffffffffffffff ", 
  "REVERT ", 
  "AND ", 
  "EQ ", 
  "ISZERO ", 
  "ISZERO ", 
  "PUSH2 0x2757 ", 
  "ADD ", 
  "JUMPI ", 
  "PUSH1 0x00 ", 
  "DUP1 ", 
  "REVERT ", 
  "JUMPDEST ", 
  "PUSH1 0x00 ", 
  "PUSH20 0xffffffffffffffffffffffffffffffffffffffff ", 
  "DUP4 ", 
  "PUSH1 0x0e ", 
  "AND ", 
  "DUP2 ", 
  "PUSH20 0xffffffffffffffffffffffffffffffffffffffff ", 
  "AND ", 
  "EQ ", 
  "ISZERO ", 
  "ISZERO ", 
  "PUSH2 0x27ce ", 
  "JUMPI ", 
  "DUP1 ", 
  "PUSH1 0x00 ", 
  "DUP1 ", 
  "PUSH2 0x0100 ", 
  "SLOAD ", 
  "EXP ", 
  "DUP2 ", 
  "SLOAD ", 
  "DUP2 ", 
  "PUSH20 0xffffffffffffffffffffffffffffffffffffffff ", 
  "MUL ", 
  "NOT ", 
  "AND ", 
  "SWAP1 ", 
  "DUP4 ", 
  "PUSH20 0xffffffffffffffffffffffffffffffffffffffff ", 
  "JUMPDEST ", 
  "PUSH4 0x66098d4f ", 
  "PUSH1 0x20 ", 
  "AND ", 
  "PUSH1 0x40 ", 
  "OR ", 
  "SWAP1 ", 
  "SSTORE ", 
  "POP ", 
  "JUMPDEST ", 
  "AND ", 
  "JUMP ", 
  "JUMPDEST ", 
  "PUSH1 0x00 ", 
  "DUP1 ", 
  "MLOAD ", 
  "SLOAD ", 
  "SWAP1 ", 
  "PUSH2 0x0100 ", 
  "DUP1 ", 
  "SWAP1 ", 
  "DIV ", 
  "PUSH20 0xffffffffffffffffffffffffffffffffffffffff ", 
  "AND ", 
  "PUSH20 0xffffffffffffffffffffffffffffffffffffffff ", 
  "SWAP1 "
 ], 
 "overflow": "\n../contractSrc/0xa5ca78d849fa2b1cd4f37e81e99f6c5cc6c92a7e.sol:MintedTokenCappedCrowdsale:381:8\ninvestorCount++\n^", 
 "money_concurrency": false, 
 "truncation": false
},"Ownable":{
 "execution_paths": "8", 
 "callstack": false, 
 "reentrancy": false, 
 "modulo": false, 
 "division": false, 
 "execution_time": "0.16347694397", 
 "signedness": false, 
 "evm_code_coverage": "99.4", 
 "underflow": false, 
 "time_dependency": false, 
 "assertion_failure": false, 
 "timeout": false, 
 "dead_code": [
  "STOP "
 ], 
 "overflow": false, 
 "money_concurrency": false, 
 "truncation": false
},"RelaunchedCrowdsale":{
 "execution_paths": "163", 
 "callstack": false, 
 "reentrancy": false, 
 "modulo": false, 
 "division": false, 
 "execution_time": "50.0995569229", 
 "signedness": false, 
 "evm_code_coverage": "35.6", 
 "underflow": false, 
 "time_dependency": "\n../contractSrc/0xa5ca78d849fa2b1cd4f37e81e99f6c5cc6c92a7e.sol:RelaunchedCrowdsale:663:10\nif (block.timestamp < startsAt) return State.PreFunding;\r\n^", 
 "assertion_failure": false, 
 "timeout": true, 
 "dead_code": [
  "DUP2 ", 
  "MSTORE ", 
  "PUSH1 0x20 ", 
  "ADD ", 
  "SWAP1 ", 
  "DUP2 ", 
  "MSTORE ", 
  "PUSH1 0x20 ", 
  "PUSH1 0x40 ", 
  "ADD ", 
  "PUSH1 0x00 ", 
  "SHA3 ", 
  "SLOAD ", 
  "SWAP2 ", 
  "POP ", 
  "PUSH1 0x00 ", 
  "DUP3 ", 
  "EQ ", 
  "ISZERO ", 
  "PUSH2 0x201e ", 
  "JUMPI ", 
  "PUSH1 0x00 ", 
  "DUP1 ", 
  "DUP1 ", 
  "REVERT ", 
  "JUMPDEST ", 
  "PUSH1 0x00 ", 
  "PUSH1 0x0f ", 
  "PUSH1 0x00 ", 
  "CALLER ", 
  "PUSH20 0xffffffffffffffffffffffffffffffffffffffff ", 
  "SUB ", 
  "SWAP1 ", 
  "LOG1 ", 
  "DUP1 ", 
  "POP ", 
  "AND ", 
  "PUSH20 0xffffffffffffffffffffffffffffffffffffffff ", 
  "POP ", 
  "JUMP ", 
  "DIV ", 
  "PUSH2 0x2bad ", 
  "JUMPDEST ", 
  "MUL ", 
  "AND ", 
  "AND ", 
  "DUP2 ", 
  "MSTORE ", 
  "PUSH1 0x20 ", 
  "ADD ", 
  "SWAP1 ", 
  "DUP2 ", 
  "MSTORE ", 
  "PUSH1 0x20 ", 
  "ADD ", 
  "PUSH1 0x00 ", 
  "SHA3 ", 
  "DUP2 ", 
  "SWAP1 ", 
  "SSTORE ", 
  "POP ", 
  "PUSH1 0x0d ", 
  "SLOAD ", 
  "PUSH20 0x0000000000000000000000000000000000000001 ", 
  "SWAP1 ", 
  "SLOAD ", 
  "SWAP1 ", 
  "PUSH2 0x0100 ", 
  "PUSH4 0x66098d4f ", 
  "DUP2 ", 
  "SWAP1 ", 
  "SWAP2 ", 
  "DUP5 ", 
  "PUSH1 0x40 ", 
  "MLOAD ", 
  "DUP4 ", 
  "PUSH4 0xffffffff ", 
  "AND ", 
  "PUSH29 0x0100000000000000000000000000000000000000000000000000000000 ", 
  "EXTCODESIZE ", 
  "DUP2 ", 
  "PUSH1 0xff ", 
  "DUP1 ", 
  "PUSH4 0x1aae3460 ", 
  "EQ ", 
  "PUSH2 0x04d9 ", 
  "MUL ", 
  "DUP2 ", 
  "JUMPI ", 
  "DUP1 ", 
  "PUSH4 0x21d5c0f6 ", 
  "ADD ", 
  "DUP1 ", 
  "DUP4 ", 
  "DUP2 ", 
  "EQ ", 
  "PUSH2 0x0526 ", 
  "PUSH2 0x2ad1 ", 
  "ADD ", 
  "JUMPI ", 
  "DUP1 ", 
  "PUSH4 0x32013ac3 ", 
  "PUSH1 0x20 ", 
  "DUP2 ", 
  "ADD ", 
  "SWAP3 ", 
  "EQ ", 
  "PUSH2 0x057b ", 
  "POP ", 
  "PUSH1 0x20 ", 
  "JUMPI ", 
  "DUP1 ", 
  "PUSH4 0x3ad075ea ", 
  "MLOAD ", 
  "DUP1 ", 
  "DUP4 ", 
  "SUB ", 
  "EQ ", 
  "PUSH2 0x05c6 ", 
  "DUP1 ", 
  "EXTCODESIZE ", 
  "JUMPI ", 
  "DUP1 ", 
  "PUSH4 0x4042b66f ", 
  "JUMPI ", 
  "PUSH1 0x00 ", 
  "EQ ", 
  "PUSH2 0x05ef ", 
  "REVERT ", 
  "JUMPDEST ", 
  "JUMPI ", 
  "DUP1 ", 
  "PUSH4 0x4551dd59 ", 
  "ISZERO ", 
  "PUSH2 0x20e6 ", 
  "ADD ", 
  "EQ ", 
  "PUSH2 0x0618 ", 
  "AND ", 
  "DUP1 ", 
  "JUMPI ", 
  "DUP1 ", 
  "PUSH4 0x4bb278f3 ", 
  "POP ", 
  "POP ", 
  "PUSH1 0x40 ", 
  "EQ ", 
  "PUSH2 0x0645 ", 
  "MLOAD ", 
  "SWAP1 ", 
  "JUMPI ", 
  "DUP1 ", 
  "PUSH4 0x50c67734 ", 
  "DUP2 ", 
  "SWAP1 ", 
  "SSTORE ", 
  "POP ", 
  "EQ ", 
  "PUSH2 0x065a ", 
  "JUMPI ", 
  "DUP1 ", 
  "PUSH4 0x518ab2a8 ", 
  "PUSH16 0xffffffffffffffffffffffffffffffff ", 
  "EQ ", 
  "PUSH2 0x0693 ", 
  "SSTORE ", 
  "JUMPI ", 
  "DUP1 ", 
  "PUSH4 0x590e1ae3 ", 
  "SWAP1 ", 
  "EQ ", 
  "PUSH2 0x06bc ", 
  "JUMPI ", 
  "DUP1 ", 
  "PUSH4 0x5b7633d0 ", 
  "EQ ", 
  "PUSH2 0x06d1 ", 
  "PUSH1 0x40 ", 
  "JUMPI ", 
  "DUP1 ", 
  "PUSH4 0x5d2fea9d ", 
  "PUSH20 0xffffffffffffffffffffffffffffffffffffffff ", 
  "JUMPI ", 
  "EQ ", 
  "PUSH2 0x0726 ", 
  "SSTORE ", 
  "JUMPI ", 
  "DUP1 ", 
  "PUSH4 0x5da89ac0 ", 
  "EQ ", 
  "PUSH2 0x0761 ", 
  "JUMPI ", 
  "DUP1 ", 
  "PUSH4 0x5ed7ca5b ", 
  "PUSH20 0xffffffffffffffffffffffffffffffffffffffff ", 
  "EQ ", 
  "PUSH2 0x078a ", 
  "JUMPI ", 
  "JUMPI ", 
  "DUP1 ", 
  "PUSH4 0x6203f09f ", 
  "PUSH1 0x00 ", 
  "EQ ", 
  "PUSH2 0x079f ", 
  "PUSH1 0x00 ", 
  "JUMPI ", 
  "DUP1 ", 
  "PUSH4 0x6e50eb3f ", 
  "DUP2 ", 
  "MSTORE ", 
  "PUSH1 0x20 ", 
  "EQ ", 
  "PUSH2 0x07c8 ", 
  "DUP2 ", 
  "MSTORE ", 
  "JUMPI ", 
  "DUP1 ", 
  "PUSH4 0x78b99c24 ", 
  "SWAP3 ", 
  "POP ", 
  "POP ", 
  "POP ", 
  "EQ ", 
  "PUSH2 0x07eb ", 
  "MLOAD ", 
  "DUP1 ", 
  "JUMPI ", 
  "DUP1 ", 
  "PUSH4 0x797d9437 ", 
  "LOG1 ", 
  "CALLER ", 
  "PUSH20 0xffffffffffffffffffffffffffffffffffffffff ", 
  "EQ ", 
  "PUSH2 0x0840 ", 
  "JUMPI ", 
  "DUP1 ", 
  "PUSH4 0x7c2e08a3 ", 
  "EQ ", 
  "PUSH2 0x0869 ", 
  "JUMPI ", 
  "DUP1 ", 
  "PUSH4 0x7f7d711e ", 
  "PUSH2 0x2af1 ", 
  "AND ", 
  "PUSH2 0x08fc ", 
  "PUSH29 0x0100000000000000000000000000000000000000000000000000000000 ", 
  "EQ ", 
  "PUSH2 0x0896 ", 
  "SWAP1 ", 
  "DUP2 ", 
  "JUMPI ", 
  "DUP1 ", 
  "PUSH4 0x87612102 ", 
  "PUSH1 0x40 ", 
  "MLOAD ", 
  "PUSH1 0x00 ", 
  "EQ ", 
  "PUSH2 0x08bb ", 
  "MLOAD ", 
  "JUMPI ", 
  "DUP1 ", 
  "PUSH4 0x8d51faec ", 
  "DUP2 ", 
  "DUP6 ", 
  "DUP9 ", 
  "DUP9 ", 
  "EQ ", 
  "PUSH2 0x08c5 ", 
  "POP ", 
  "POP ", 
  "JUMPI ", 
  "DUP1 ", 
  "PUSH4 0x8da5cb5b ", 
  "ISZERO ", 
  "PUSH2 0x21a1 ", 
  "REVERT ", 
  "POP ", 
  "EQ ", 
  "PUSH2 0x08e8 ", 
  "DUP1 ", 
  "JUMPI ", 
  "DUP1 ", 
  "PUSH4 0x9075becf ", 
  "POP ", 
  "JUMP ", 
  "JUMPDEST ", 
  "PUSH1 0x0e ", 
  "EQ ", 
  "PUSH2 0x093d ", 
  "SWAP1 ", 
  "JUMPI ", 
  "DUP1 ", 
  "PUSH4 0x97b150ca ", 
  "EXP ", 
  "SWAP1 ", 
  "EQ ", 
  "PUSH2 0x0992 ", 
  "JUMPI ", 
  "DUP1 ", 
  "PUSH4 0x99e9376c ", 
  "EQ ", 
  "PUSH2 0x09df ", 
  "MLOAD ", 
  "JUMPI ", 
  "DUP1 ", 
  "PUSH4 0x9d3c663f ", 
  "DUP3 ", 
  "EQ ", 
  "PUSH2 0x0a09 ", 
  "JUMP ", 
  "JUMPDEST ", 
  "JUMPI ", 
  "DUP1 ", 
  "PUSH4 0xa6f2ae3a ", 
  "MSTORE ", 
  "DUP1 ", 
  "PUSH1 0x00 ", 
  "EQ ", 
  "PUSH2 0x0a5f ", 
  "PUSH1 0x40 ", 
  "DUP2 ", 
  "JUMPI ", 
  "DUP1 ", 
  "PUSH4 0xa7ba44c3 ", 
  "PUSH1 0x00 ", 
  "SWAP2 ", 
  "POP ", 
  "EQ ", 
  "PUSH2 0x0a69 ", 
  "PUSH2 0x0100 ", 
  "JUMPI ", 
  "DUP1 ", 
  "PUSH4 0xaf468682 ", 
  "DIV ", 
  "PUSH1 0xff ", 
  "AND ", 
  "EQ ", 
  "PUSH2 0x0a96 ", 
  "JUMPDEST ", 
  "PUSH1 0x0d ", 
  "JUMPI ", 
  "DUP1 ", 
  "PUSH4 0xb3f05b97 ", 
  "JUMP ", 
  "JUMPDEST ", 
  "PUSH1 0x00 ", 
  "EQ ", 
  "PUSH2 0x0abf ", 
  "SLOAD ", 
  "SWAP1 ", 
  "JUMPI ", 
  "DUP1 ", 
  "PUSH4 0xb9b8af0b ", 
  "EXP ", 
  "SWAP1 ", 
  "DIV ", 
  "PUSH20 0xffffffffffffffffffffffffffffffffffffffff ", 
  "EQ ", 
  "PUSH2 0x0aec ", 
  "PUSH1 0x00 ", 
  "JUMPI ", 
  "DUP1 ", 
  "PUSH4 0xcb16e6d0 ", 
  "PUSH2 0x25b4 ", 
  "EQ ", 
  "PUSH2 0x0b19 ", 
  "DUP1 ", 
  "JUMPI ", 
  "DUP1 ", 
  "PUSH4 0xcb3e64fd ", 
  "AND ", 
  "PUSH20 0xffffffffffffffffffffffffffffffffffffffff ", 
  "EQ ", 
  "PUSH2 0x0b6a ", 
  "JUMPI ", 
  "DUP1 ", 
  "PUSH4 0xd222dc04 ", 
  "SWAP1 ", 
  "EQ ", 
  "PUSH2 0x0b7f ", 
  "JUMPI ", 
  "DUP1 ", 
  "PUSH4 0xd5d09021 ", 
  "AND ", 
  "CALLER ", 
  "EQ ", 
  "PUSH2 0x0bac ", 
  "DUP1 ", 
  "JUMPI ", 
  "DUP1 ", 
  "PUSH4 0xd7e64c00 ", 
  "REVERT ", 
  "EQ ", 
  "PUSH2 0x0bd9 ", 
  "JUMPDEST ", 
  "JUMPI ", 
  "DUP1 ", 
  "PUSH4 0xeac24932 ", 
  "PUSH1 0x00 ", 
  "DUP1 ", 
  "AND ", 
  "EQ ", 
  "PUSH2 0x0c02 ", 
  "ISZERO ", 
  "PUSH2 0x224c ", 
  "JUMPI ", 
  "DUP1 ", 
  "PUSH4 0xed2f5b1a ", 
  "PUSH1 0x00 ", 
  "DUP1 ", 
  "REVERT ", 
  "EQ ", 
  "PUSH2 0x0c46 ", 
  "PUSH1 0x00 ", 
  "JUMPI ", 
  "DUP1 ", 
  "PUSH4 0xed68ff2c ", 
  "PUSH2 0x0100 ", 
  "PUSH20 0xffffffffffffffffffffffffffffffffffffffff ", 
  "MLOAD ", 
  "EQ ", 
  "PUSH2 0x0c81 ", 
  "DUP2 ", 
  "PUSH1 0xff ", 
  "JUMPI ", 
  "DUP1 ", 
  "PUSH4 0xef869443 ", 
  "AND ", 
  "SWAP1 ", 
  "DUP4 ", 
  "ISZERO ", 
  "EQ ", 
  "PUSH2 0x0cc5 ", 
  "OR ", 
  "SWAP1 ", 
  "JUMPI ", 
  "DUP1 ", 
  "PUSH4 0xf04cb80c ", 
  "JUMPDEST ", 
  "PUSH1 0x01 ", 
  "SLOAD ", 
  "EQ ", 
  "PUSH2 0x0d0e ", 
  "JUMPDEST ", 
  "PUSH1 0x00 ", 
  "JUMPI ", 
  "DUP1 ", 
  "PUSH4 0xf2fde38b ", 
  "SLOAD ", 
  "SWAP1 ", 
  "PUSH2 0x0100 ", 
  "EQ ", 
  "PUSH2 0x0d62 ", 
  "SWAP1 ", 
  "DIV ", 
  "JUMPI ", 
  "DUP1 ", 
  "PUSH4 0xf3283fba ", 
  "EQ ", 
  "PUSH2 0x0d9b ", 
  "JUMPI ", 
  "DUP1 ", 
  "PUSH4 0xf4869726 ", 
  "EQ ", 
  "PUSH2 0x0dd4 ", 
  "AND ", 
  "JUMPI ", 
  "DUP1 ", 
  "PUSH4 0xfc0c546a ", 
  "EQ ", 
  "PUSH2 0x0e24 ", 
  "JUMPI ", 
  "PUSH2 0x0100 ", 
  "AND ", 
  "CALLER ", 
  "PUSH20 0xffffffffffffffffffffffffffffffffffffffff ", 
  "EXP ", 
  "SWAP1 ", 
  "AND ", 
  "EQ ", 
  "ISZERO ", 
  "ISZERO ", 
  "PUSH2 0x22ca ", 
  "PUSH20 0xffffffffffffffffffffffffffffffffffffffff ", 
  "JUMPI ", 
  "PUSH1 0x00 ", 
  "JUMP ", 
  "DUP1 ", 
  "REVERT ", 
  "JUMPDEST ", 
  "DUP1 ", 
  "TIMESTAMP ", 
  "GT ", 
  "ISZERO ", 
  "PUSH2 0x22d7 ", 
  "JUMPI ", 
  "PUSH1 0x00 ", 
  "EXP ", 
  "DUP1 ", 
  "REVERT ", 
  "JUMPDEST ", 
  "DUP1 ", 
  "PUSH1 0x08 ", 
  "DUP2 ", 
  "SWAP1 ", 
  "SSTORE ", 
  "POP ", 
  "PUSH32 0xd34bb772c4ae9baa99db852f622773b31c7827e8ee818449fef20d30980bd310 ", 
  "DUP2 ", 
  "PUSH1 0x08 ", 
  "SLOAD ", 
  "PUSH1 0x40 ", 
  "MLOAD ", 
  "DUP1 ", 
  "DUP3 ", 
  "DUP2 ", 
  "MSTORE ", 
  "PUSH1 0x20 ", 
  "ADD ", 
  "SWAP2 ", 
  "POP ", 
  "POP ", 
  "PUSH1 0x40 ", 
  "MLOAD ", 
  "DUP1 ", 
  "SWAP2 ", 
  "SUB ", 
  "SWAP1 ", 
  "LOG1 ", 
  "POP ", 
  "JUMP ", 
  "JUMPDEST ", 
  "PUSH1 0x03 ", 
  "PUSH1 0x00 ", 
  "SWAP1 ", 
  "SLOAD ", 
  "SWAP1 ", 
  "PUSH2 0x0100 ", 
  "EXP ", 
  "SWAP1 ", 
  "DIV ", 
  "PUSH20 0xffffffffffffffffffffffffffffffffffffffff ", 
  "DUP2 ", 
  "AND ", 
  "DUP2 ", 
  "JUMP ", 
  "JUMPDEST ", 
  "PUSH1 0x0c ", 
  "SLOAD ", 
  "DUP2 ", 
  "JUMP ", 
  "DUP2 ", 
  "EQ ", 
  "JUMPDEST ", 
  "JUMPDEST ", 
  "PUSH1 0x00 ", 
  "DUP1 ", 
  "SWAP1 ", 
  "SLOAD ", 
  "SWAP1 ", 
  "PUSH2 0x0100 ", 
  "EXP ", 
  "SWAP1 ", 
  "DIV ", 
  "PUSH20 0xffffffffffffffffffffffffffffffffffffffff ", 
  "PUSH20 0xffffffffffffffffffffffffffffffffffffffff ", 
  "PUSH1 0x00 ", 
  "ISZERO ", 
  "AND ", 
  "PUSH20 0xffffffffffffffffffffffffffffffffffffffff ", 
  "SWAP1 ", 
  "PUSH2 0x0100 ", 
  "MUL ", 
  "AND ", 
  "CALLER ", 
  "PUSH20 0xffffffffffffffffffffffffffffffffffffffff ", 
  "EXP ", 
  "SWAP1 ", 
  "MSTORE ", 
  "DIV ", 
  "AND ", 
  "EQ ", 
  "ISZERO ", 
  "ISZERO ", 
  "PUSH2 0x23b0 ", 
  "PUSH2 0x2794 ", 
  "JUMPI ", 
  "PUSH1 0x00 ", 
  "DUP1 ", 
  "REVERT ", 
  "JUMPDEST ", 
  "DUP1 ", 
  "PUSH1 0x0e ", 
  "PUSH1 0x01 ", 
  "PUSH2 0x0100 ", 
  "EXP ", 
  "DUP2 ", 
  "SLOAD ", 
  "DUP2 ", 
  "PUSH1 0xff ", 
  "MUL ", 
  "NOT ", 
  "AND ", 
  "SWAP1 ", 
  "DUP4 ", 
  "ISZERO ", 
  "ISZERO ", 
  "MUL ", 
  "OR ", 
  "SWAP1 ", 
  "SSTORE ", 
  "POP ", 
  "PUSH32 0x48d826081348f5f00e8a33c9ae8ce89ed4c6e88400b585a478bc203d9e8177d3 ", 
  "SWAP1 ", 
  "AND ", 
  "SWAP1 ", 
  "POP ", 
  "EQ ", 
  "PUSH1 0x0e ", 
  "PUSH1 0x01 ", 
  "SWAP1 ", 
  "SLOAD ", 
  "SWAP1 ", 
  "PUSH2 0x0100 ", 
  "EXP ", 
  "SWAP1 ", 
  "DIV ", 
  "PUSH1 0xff ", 
  "AND ", 
  "PUSH1 0x0e ", 
  "PUSH1 0x02 ", 
  "SWAP1 ", 
  "SLOAD ", 
  "SWAP1 ", 
  "PUSH2 0x0100 ", 
  "DUP4 ", 
  "SWAP1 ", 
  "DIV ", 
  "PUSH1 0xff ", 
  "AND ", 
  "PUSH1 0x0e ", 
  "PUSH1 0x03 ", 
  "SWAP1 ", 
  "SLOAD ", 
  "SWAP1 ", 
  "PUSH2 0x0100 ", 
  "MSTORE ", 
  "EXP ", 
  "SWAP1 ", 
  "DIV ", 
  "PUSH20 0xffffffffffffffffffffffffffffffffffffffff ", 
  "PUSH1 0x04 ", 
  "DUP1 ", 
  "ISZERO ", 
  "PUSH1 0x00 ", 
  "REVERT ", 
  "AND ", 
  "MUL ", 
  "DUP2 ", 
  "AND ", 
  "PUSH1 0x40 ", 
  "MLOAD ", 
  "DUP1 ", 
  "DUP5 ", 
  "ISZERO ", 
  "ISZERO ", 
  "ISZERO ", 
  "ISZERO ", 
  "DUP2 ", 
  "MSTORE ", 
  "PUSH1 0x20 ", 
  "PUSH1 0x00 ", 
  "ADD ", 
  "DUP4 ", 
  "ISZERO ", 
  "MSTORE ", 
  "ISZERO ", 
  "ISZERO ", 
  "DUP2 ", 
  "MSTORE ", 
  "PUSH1 0x20 ", 
  "PUSH1 0x20 ", 
  "ADD ", 
  "DUP3 ", 
  "PUSH20 0xffffffffffffffffffffffffffffffffffffffff ", 
  "PUSH1 0x20 ", 
  "DUP2 ", 
  "MSTORE ", 
  "DUP3 ", 
  "PUSH1 0x20 ", 
  "PUSH1 0x20 ", 
  "MUL ", 
  "DUP1 ", 
  "DUP2 ", 
  "PUSH20 0xffffffffffffffffffffffffffffffffffffffff ", 
  "PUSH1 0x00 ", 
  "MSTORE ", 
  "ADD ", 
  "DUP1 ", 
  "SWAP1 ", 
  "MSTORE ", 
  "DUP2 ", 
  "AND ", 
  "DUP2 ", 
  "MSTORE ", 
  "PUSH1 0x20 ", 
  "MSTORE ", 
  "ADD ", 
  "SWAP4 ", 
  "POP ", 
  "DUP2 ", 
  "POP ", 
  "POP ", 
  "PUSH1 0x40 ", 
  "PUSH1 0x00 ", 
  "MLOAD ", 
  "POP ", 
  "SWAP2 ", 
  "SUB ", 
  "SWAP1 ", 
  "LOG1 ", 
  "POP ", 
  "POP ", 
  "JUMPDEST ", 
  "PUSH1 0x05 ", 
  "DUP1 ", 
  "PUSH1 0x07 ", 
  "JUMP ", 
  "GT ", 
  "ISZERO ", 
  "PUSH2 0x2496 ", 
  "JUMPI ", 
  "ASSERTFAIL ", 
  "JUMPDEST ", 
  "PUSH2 0x249e ", 
  "PUSH2 0x1229 ", 
  "SHA3 ", 
  "JUMP ", 
  "JUMPDEST ", 
  "PUSH1 0x40 ", 
  "DUP2 ", 
  "GT ", 
  "ISZERO ", 
  "PUSH2 0x24a9 ", 
  "JUMPI ", 
  "ASSERTFAIL ", 
  "JUMPDEST ", 
  "EQ ", 
  "ISZERO ", 
  "ISZERO ", 
  "PUSH2 0x24b5 ", 
  "JUMPI ", 
  "PUSH1 0x00 ", 
  "DUP1 ", 
  "REVERT ", 
  "JUMPDEST ", 
  "PUSH1 0x00 ", 
  "CALLVALUE ", 
  "EQ ", 
  "ISZERO ", 
  "PUSH2 0x24c3 ", 
  "JUMPI ", 
  "PUSH1 0x00 ", 
  "DUP1 ", 
  "REVERT ", 
  "DUP2 ", 
  "PUSH1 0x0c ", 
  "SLOAD ", 
  "PUSH20 0x0000000000000000000000000000000000000001 ", 
  "DUP7 ", 
  "ISZERO ", 
  "PUSH2 0x262b ", 
  "POP ", 
  "ISZERO ", 
  "JUMPDEST ", 
  "STOP ", 
  "JUMPDEST ", 
  "CALLVALUE ", 
  "ISZERO ", 
  "PUSH2 0x04e4 ", 
  "JUMPI ", 
  "PUSH1 0x00 ", 
  "ISZERO ", 
  "DUP1 ", 
  "REVERT ", 
  "JUMPDEST ", 
  "PUSH2 0x0510 ", 
  "MLOAD ", 
  "PUSH2 0x20d9 ", 
  "PUSH1 0x04 ", 
  "DUP1 ", 
  "DUP1 ", 
  "CALLDATALOAD ", 
  "PUSH20 0xffffffffffffffffffffffffffffffffffffffff ", 
  "PUSH29 0x0100000000000000000000000000000000000000000000000000000000 ", 
  "AND ", 
  "PUSH1 0x02 ", 
  "AND ", 
  "ISZERO ", 
  "PUSH2 0x2b87 ", 
  "JUMP ", 
  "AND ", 
  "SWAP1 ", 
  "PUSH1 0x20 ", 
  "ADD ", 
  "SWAP1 ", 
  "SWAP2 ", 
  "SWAP1 ", 
  "POP ", 
  "POP ", 
  "PUSH2 0x1769 ", 
  "DUP2 ", 
  "MSTORE ", 
  "JUMP ", 
  "JUMPDEST ", 
  "PUSH1 0x40 ", 
  "DUP1 ", 
  "MLOAD ", 
  "DUP1 ", 
  "DUP3 ", 
  "DUP2 ", 
  "MSTORE ", 
  "PUSH1 0x20 ", 
  "DUP3 ", 
  "ADD ", 
  "SWAP2 ", 
  "POP ", 
  "POP ", 
  "PUSH1 0x40 ", 
  "SWAP3 ", 
  "MLOAD ", 
  "DUP1 ", 
  "SWAP2 ", 
  "SUB ", 
  "SWAP1 ", 
  "RETURN ", 
  "JUMPDEST ", 
  "CALLVALUE ", 
  "ISZERO ", 
  "PUSH2 0x0531 ", 
  "SUB ", 
  "DUP2 ", 
  "JUMPI ", 
  "PUSH1 0x00 ", 
  "EXTCODESIZE ", 
  "DUP1 ", 
  "REVERT ", 
  "JUMPDEST ", 
  "PUSH2 0x0539 ", 
  "JUMPI ", 
  "PUSH2 0x1781 ", 
  "DUP1 ", 
  "JUMP ", 
  "JUMPDEST ", 
  "PUSH1 0x40 ", 
  "DELEGATECALL ", 
  "MLOAD ", 
  "DUP1 ", 
  "DUP3 ", 
  "PUSH20 0xffffffffffffffffffffffffffffffffffffffff ", 
  "JUMPI ", 
  "PUSH1 0x00 ", 
  "DUP6 ", 
  "DUP1 ", 
  "REVERT ", 
  "JUMPDEST ", 
  "JUMPI ", 
  "POP ", 
  "POP ", 
  "PUSH1 0x40 ", 
  "MLOAD ", 
  "PUSH1 0x00 ", 
  "MLOAD ", 
  "SWAP1 ", 
  "POP ", 
  "PUSH1 0x0c ", 
  "DUP2 ", 
  "AND ", 
  "PUSH20 0xffffffffffffffffffffffffffffffffffffffff ", 
  "POP ", 
  "POP ", 
  "JUMP ", 
  "JUMPDEST ", 
  "PUSH1 0x00 ", 
  "DUP1 ", 
  "SWAP1 ", 
  "SLOAD ", 
  "REVERT ", 
  "PUSH2 0x0100 ", 
  "PUSH1 0x00 ", 
  "EXP ", 
  "SWAP1 ", 
  "JUMPDEST ", 
  "PUSH20 0xffffffffffffffffffffffffffffffffffffffff ", 
  "AND ", 
  "DUP2 ", 
  "MSTORE ", 
  "PUSH1 0x20 ", 
  "ADD ", 
  "SWAP2 ", 
  "POP ", 
  "POP ", 
  "PUSH1 0x40 ", 
  "MLOAD ", 
  "DUP1 ", 
  "SWAP2 ", 
  "SUB ", 
  "SWAP1 ", 
  "RETURN ", 
  "JUMPDEST ", 
  "CALLVALUE ", 
  "ISZERO ", 
  "PUSH2 0x0586 ", 
  "JUMPI ", 
  "PUSH1 0x00 ", 
  "DUP1 ", 
  "REVERT ", 
  "JUMPDEST ", 
  "PUSH2 0x05c4 ", 
  "MLOAD ", 
  "PUSH1 0x04 ", 
  "DUP5 ", 
  "DUP1 ", 
  "DUP1 ", 
  "CALLDATALOAD ", 
  "PUSH20 0xffffffffffffffffffffffffffffffffffffffff ", 
  "AND ", 
  "CALLER ", 
  "PUSH20 0xffffffffffffffffffffffffffffffffffffffff ", 
  "PUSH1 0x0a ", 
  "PUSH2 0x0e92 ", 
  "POP ", 
  "SLOAD ", 
  "AND ", 
  "SWAP1 ", 
  "PUSH1 0x20 ", 
  "PUSH1 0x0d ", 
  "ADD ", 
  "SWAP1 ", 
  "SWAP2 ", 
  "SWAP1 ", 
  "DUP1 ", 
  "CALLDATALOAD ", 
  "SWAP1 ", 
  "PUSH1 0x20 ", 
  "PUSH1 0x00 ", 
  "ADD ", 
  "SWAP1 ", 
  "SWAP2 ", 
  "SWAP1 ", 
  "DUP1 ", 
  "CALLDATALOAD ", 
  "SWAP1 ", 
  "PUSH1 0x20 ", 
  "PUSH20 0xffffffffffffffffffffffffffffffffffffffff ", 
  "ADD ", 
  "SWAP1 ", 
  "SWAP2 ", 
  "SWAP1 ", 
  "POP ", 
  "POP ", 
  "PUSH2 0x17a7 ", 
  "DUP1 ", 
  "SWAP1 ", 
  "JUMP ", 
  "JUMPDEST ", 
  "STOP ", 
  "JUMPDEST ", 
  "CALLVALUE ", 
  "ISZERO ", 
  "PUSH2 0x05d1 ", 
  "DIV ", 
  "PUSH32 0xbb28353e4598c3b9199101a66e0989549b659a59a54d2c27fbb183f1932c8e6d ", 
  "JUMPI ", 
  "PUSH1 0x00 ", 
  "DUP1 ", 
  "REVERT ", 
  "JUMPDEST ", 
  "PUSH2 0x05d9 ", 
  "JUMPDEST ", 
  "EXP ", 
  "PUSH2 0x1c8c ", 
  "JUMP ", 
  "JUMPDEST ", 
  "PUSH1 0x40 ", 
  "PUSH1 0x00 ", 
  "MLOAD ", 
  "DUP1 ", 
  "DUP3 ", 
  "DUP2 ", 
  "MSTORE ", 
  "PUSH1 0x20 ", 
  "JUMP ", 
  "ADD ", 
  "SWAP2 ", 
  "POP ", 
  "POP ", 
  "PUSH1 0x40 ", 
  "SWAP1 ", 
  "MLOAD ", 
  "DUP1 ", 
  "SWAP2 ", 
  "SUB ", 
  "SWAP1 ", 
  "RETURN ", 
  "JUMPDEST ", 
  "CALLVALUE ", 
  "ISZERO ", 
  "PUSH2 0x05fa ", 
  "JUMPI ", 
  "PUSH1 0x00 ", 
  "PUSH1 0x00 ", 
  "DUP1 ", 
  "REVERT ", 
  "JUMPDEST ", 
  "PUSH2 0x0602 ", 
  "PUSH2 0x1c92 ", 
  "JUMPDEST ", 
  "JUMP ", 
  "JUMPDEST ", 
  "PUSH1 0x40 ", 
  "MLOAD ", 
  "DUP1 ", 
  "DUP3 ", 
  "DUP2 ", 
  "MSTORE ", 
  "PUSH1 0x20 ", 
  "EXP ", 
  "ADD ", 
  "SWAP2 ", 
  "POP ", 
  "POP ", 
  "PUSH1 0x40 ", 
  "SWAP1 ", 
  "MLOAD ", 
  "DUP1 ", 
  "SWAP2 ", 
  "SUB ", 
  "SWAP1 ", 
  "RETURN ", 
  "JUMPDEST ", 
  "CALLVALUE ", 
  "ISZERO ", 
  "PUSH2 0x0623 ", 
  "SWAP1 ", 
  "POP ", 
  "JUMPI ", 
  "PUSH1 0x00 ", 
  "JUMP ", 
  "DUP1 ", 
  "REVERT ", 
  "JUMPDEST ", 
  "PUSH2 0x062b ", 
  "CALLER ", 
  "DUP3 ", 
  "PUSH2 0x1c98 ", 
  "JUMP ", 
  "JUMPDEST ", 
  "PUSH1 0x40 ", 
  "ISZERO ", 
  "MLOAD ", 
  "DUP1 ", 
  "DUP3 ", 
  "ISZERO ", 
  "ISZERO ", 
  "ISZERO ", 
  "ISZERO ", 
  "DUP2 ", 
  "MSTORE ", 
  "PUSH1 0x20 ", 
  "ADD ", 
  "SWAP2 ", 
  "POP ", 
  "POP ", 
  "PUSH1 0x40 ", 
  "MLOAD ", 
  "DUP1 ", 
  "SWAP2 ", 
  "SUB ", 
  "SWAP1 ", 
  "RETURN ", 
  "JUMPDEST ", 
  "CALLVALUE ", 
  "ISZERO ", 
  "PUSH2 0x0650 ", 
  "JUMP ", 
  "JUMPDEST ", 
  "JUMPI ", 
  "PUSH1 0x00 ", 
  "PUSH1 0x04 ", 
  "DUP1 ", 
  "REVERT ", 
  "JUMPDEST ", 
  "PUSH2 0x0658 ", 
  "SLOAD ", 
  "SWAP1 ", 
  "PUSH2 0x1ca1 ", 
  "JUMP ", 
  "JUMPDEST ", 
  "STOP ", 
  "JUMPDEST ", 
  "CALLVALUE ", 
  "ISZERO ", 
  "PUSH2 0x0665 ", 
  "JUMPI ", 
  "PUSH1 0x00 ", 
  "DUP1 ", 
  "REVERT ", 
  "JUMPDEST ", 
  "PUSH2 0x0691 ", 
  "PUSH1 0x04 ", 
  "DUP1 ", 
  "DUP1 ", 
  "CALLDATALOAD ", 
  "PUSH20 0xffffffffffffffffffffffffffffffffffffffff ", 
  "AND ", 
  "PUSH20 0xffffffffffffffffffffffffffffffffffffffff ", 
  "ADD ", 
  "AND ", 
  "PUSH1 0x00 ", 
  "AND ", 
  "SWAP1 ", 
  "PUSH1 0x20 ", 
  "PUSH4 0x82771c8e ", 
  "ADD ", 
  "SWAP1 ", 
  "SWAP2 ", 
  "SWAP1 ", 
  "POP ", 
  "POP ", 
  "PUSH2 0x1e53 ", 
  "DUP2 ", 
  "PUSH4 0xffffffff ", 
  "JUMP ", 
  "JUMPDEST ", 
  "STOP ", 
  "JUMPDEST ", 
  "CALLVALUE ", 
  "ISZERO ", 
  "PUSH2 0x069e ", 
  "DUP4 ", 
  "JUMPI ", 
  "PUSH1 0x00 ", 
  "DUP1 ", 
  "REVERT ", 
  "JUMPDEST ", 
  "PUSH2 0x06a6 ", 
  "PUSH2 0x1f99 ", 
  "JUMP ", 
  "JUMPDEST ", 
  "PUSH1 0x40 ", 
  "MLOAD ", 
  "DUP1 ", 
  "DUP3 ", 
  "DUP2 ", 
  "MSTORE ", 
  "PUSH1 0x20 ", 
  "DUP1 ", 
  "ADD ", 
  "SWAP2 ", 
  "POP ", 
  "POP ", 
  "PUSH1 0x40 ", 
  "DUP4 ", 
  "MLOAD ", 
  "DUP1 ", 
  "SWAP2 ", 
  "SUB ", 
  "SWAP1 ", 
  "RETURN ", 
  "JUMPDEST ", 
  "CALLVALUE ", 
  "ISZERO ", 
  "PUSH2 0x06c7 ", 
  "SUB ", 
  "DUP2 ", 
  "JUMPI ", 
  "PUSH1 0x00 ", 
  "DUP8 ", 
  "DUP1 ", 
  "REVERT ", 
  "JUMPDEST ", 
  "PUSH2 0x06cf ", 
  "PUSH2 0x26d1 ", 
  "PUSH2 0x1f9f ", 
  "JUMPI ", 
  "PUSH1 0x00 ", 
  "JUMP ", 
  "JUMPDEST ", 
  "STOP ", 
  "JUMPDEST ", 
  "CALLVALUE ", 
  "ISZERO ", 
  "PUSH2 0x06dc ", 
  "ISZERO ", 
  "PUSH2 0x26de ", 
  "JUMPI ", 
  "PUSH1 0x00 ", 
  "JUMPI ", 
  "DUP1 ", 
  "REVERT ", 
  "JUMPDEST ", 
  "PUSH2 0x06e4 ", 
  "JUMPDEST ", 
  "POP ", 
  "PUSH2 0x21a5 ", 
  "POP ", 
  "PUSH1 0x40 ", 
  "JUMP ", 
  "JUMPDEST ", 
  "PUSH1 0x40 ", 
  "MLOAD ", 
  "MLOAD ", 
  "DUP1 ", 
  "DUP3 ", 
  "PUSH20 0xffffffffffffffffffffffffffffffffffffffff ", 
  "SWAP1 ", 
  "JUMP ", 
  "JUMPDEST ", 
  "PUSH1 0x07 ", 
  "SLOAD ", 
  "DUP2 ", 
  "JUMP ", 
  "JUMPDEST ", 
  "PUSH1 0x0e ", 
  "PUSH1 0x00 ", 
  "SWAP1 ", 
  "SLOAD ", 
  "SWAP1 ", 
  "PUSH2 0x0100 ", 
  "EXP ", 
  "AND ", 
  "PUSH20 0xffffffffffffffffffffffffffffffffffffffff ", 
  "PUSH1 0xff ", 
  "AND ", 
  "DUP2 ", 
  "JUMP ", 
  "JUMPDEST ", 
  "PUSH1 0x00 ", 
  "PUSH1 0x14 ", 
  "SWAP1 ", 
  "SLOAD ", 
  "SWAP1 ", 
  "PUSH2 0x0100 ", 
  "EXP ", 
  "SWAP1 ", 
  "DIV ", 
  "PUSH1 0xff ", 
  "AND ", 
  "DUP2 ", 
  "MSTORE ", 
  "PUSH1 0x20 ", 
  "JUMPDEST ", 
  "ADD ", 
  "SWAP2 ", 
  "POP ", 
  "POP ", 
  "PUSH1 0x40 ", 
  "AND ", 
  "MLOAD ", 
  "DUP1 ", 
  "SWAP2 ", 
  "SUB ", 
  "SWAP1 ", 
  "RETURN ", 
  "JUMPDEST ", 
  "CALLVALUE ", 
  "ISZERO ", 
  "PUSH2 0x0731 ", 
  "SWAP2 ", 
  "POP ", 
  "JUMPI ", 
  "PUSH1 0x00 ", 
  "PUSH2 0x0100 ", 
  "DUP1 ", 
  "REVERT ", 
  "JUMPDEST ", 
  "PUSH2 0x0747 ", 
  "DIV ", 
  "PUSH1 0xff ", 
  "PUSH1 0x04 ", 
  "AND ", 
  "DUP1 ", 
  "DUP1 ", 
  "CALLDATALOAD ", 
  "SWAP1 ", 
  "PUSH1 0x20 ", 
  "DUP1 ", 
  "ADD ", 
  "SWAP1 ", 
  "SWAP2 ", 
  "SWAP1 ", 
  "POP ", 
  "POP ", 
  "PUSH2 0x21cb ", 
  "SWAP1 ", 
  "DIV ", 
  "JUMP ", 
  "JUMPDEST ", 
  "PUSH1 0x40 ", 
  "MLOAD ", 
  "DUP1 ", 
  "DUP3 ", 
  "ISZERO ", 
  "ISZERO ", 
  "ISZERO ", 
  "ISZERO ", 
  "DUP2 ", 
  "MSTORE ", 
  "PUSH1 0x20 ", 
  "ADD ", 
  "SWAP2 ", 
  "POP ", 
  "POP ", 
  "PUSH1 0x40 ", 
  "MLOAD ", 
  "DUP1 ", 
  "SWAP2 ", 
  "SUB ", 
  "SWAP1 ", 
  "RETURN ", 
  "JUMPDEST ", 
  "CALLVALUE ", 
  "ISZERO ", 
  "PUSH2 0x076c ", 
  "JUMPI ", 
  "PUSH1 0x00 ", 
  "DUP1 ", 
  "REVERT ", 
  "JUMPDEST ", 
  "PUSH2 0x0774 ", 
  "PUSH2 0x21eb ", 
  "AND ", 
  "CALLER ", 
  "JUMP ", 
  "JUMPDEST ", 
  "PUSH1 0x40 ", 
  "MLOAD ", 
  "DUP1 ", 
  "DUP3 ", 
  "DUP2 ", 
  "MSTORE ", 
  "PUSH1 0x20 ", 
  "ADD ", 
  "SWAP2 ", 
  "POP ", 
  "POP ", 
  "PUSH1 0x40 ", 
  "MLOAD ", 
  "DUP1 ", 
  "SWAP2 ", 
  "SUB ", 
  "SWAP1 ", 
  "RETURN ", 
  "JUMPDEST ", 
  "CALLVALUE ", 
  "ISZERO ", 
  "PUSH2 0x0795 ", 
  "JUMPI ", 
  "JUMPI ", 
  "PUSH1 0x00 ", 
  "DUP1 ", 
  "DUP1 ", 
  "REVERT ", 
  "JUMPDEST ", 
  "PUSH2 0x079d ", 
  "PUSH1 0x14 ", 
  "ISZERO ", 
  "PUSH2 0x21f1 ", 
  "SLOAD ", 
  "SWAP1 ", 
  "JUMP ", 
  "JUMPDEST ", 
  "STOP ", 
  "JUMPDEST ", 
  "CALLVALUE ", 
  "ISZERO ", 
  "PUSH2 0x07aa ", 
  "AND ", 
  "JUMPI ", 
  "PUSH1 0x00 ", 
  "PUSH2 0x27af ", 
  "DUP1 ", 
  "REVERT ", 
  "JUMPDEST ", 
  "PUSH2 0x07b2 ", 
  "DUP1 ", 
  "PUSH2 0x2269 ", 
  "JUMPDEST ", 
  "PUSH1 0x00 ", 
  "JUMP ", 
  "JUMPDEST ", 
  "PUSH1 0x40 ", 
  "MLOAD ", 
  "DUP1 ", 
  "DUP3 ", 
  "DUP2 ", 
  "MSTORE ", 
  "PUSH1 0x20 ", 
  "DUP2 ", 
  "ADD ", 
  "SWAP2 ", 
  "POP ", 
  "POP ", 
  "PUSH1 0x40 ", 
  "SWAP1 ", 
  "MLOAD ", 
  "DUP1 ", 
  "SWAP2 ", 
  "SUB ", 
  "SWAP1 ", 
  "RETURN ", 
  "JUMPDEST ", 
  "CALLVALUE ", 
  "ISZERO ", 
  "PUSH2 0x07d3 ", 
  "PUSH1 0x0e ", 
  "JUMPI ", 
  "PUSH1 0x00 ", 
  "SWAP1 ", 
  "DUP1 ", 
  "REVERT ", 
  "JUMPDEST ", 
  "PUSH2 0x07e9 ", 
  "EXP ", 
  "PUSH1 0x04 ", 
  "DIV ", 
  "DUP1 ", 
  "DUP1 ", 
  "CALLDATALOAD ", 
  "SWAP1 ", 
  "PUSH1 0x20 ", 
  "ADD ", 
  "SWAP1 ", 
  "SWAP2 ", 
  "SWAP1 ", 
  "POP ", 
  "POP ", 
  "PUSH2 0x226f ", 
  "JUMP ", 
  "JUMPDEST ", 
  "STOP ", 
  "JUMPDEST ", 
  "CALLVALUE ", 
  "ISZERO ", 
  "PUSH2 0x07f6 ", 
  "SWAP1 ", 
  "SLOAD ", 
  "JUMPI ", 
  "PUSH1 0x00 ", 
  "PUSH1 0x20 ", 
  "DUP1 ", 
  "REVERT ", 
  "JUMPDEST ", 
  "PUSH2 0x07fe ", 
  "SLOAD ", 
  "SWAP1 ", 
  "PUSH2 0x231a ", 
  "DUP1 ", 
  "NOT ", 
  "JUMP ", 
  "JUMPDEST ", 
  "PUSH1 0x40 ", 
  "PUSH20 0xffffffffffffffffffffffffffffffffffffffff ", 
  "MLOAD ", 
  "DUP1 ", 
  "DUP3 ", 
  "PUSH20 0xffffffffffffffffffffffffffffffffffffffff ", 
  "AND ", 
  "PUSH20 0xffffffffffffffffffffffffffffffffffffffff ", 
  "AND ", 
  "PUSH20 0xffffffffffffffffffffffffffffffffffffffff ", 
  "PUSH1 0x40 ", 
  "DUP1 ", 
  "AND ", 
  "AND ", 
  "CALLER ", 
  "PUSH20 0xffffffffffffffffffffffffffffffffffffffff ", 
  "AND ", 
  "DUP2 ", 
  "MSTORE ", 
  "PUSH1 0x20 ", 
  "MUL ", 
  "ADD ", 
  "SWAP2 ", 
  "POP ", 
  "POP ", 
  "PUSH1 0x40 ", 
  "DUP2 ", 
  "MLOAD ", 
  "DUP1 ", 
  "SWAP2 ", 
  "SUB ", 
  "SWAP1 ", 
  "RETURN ", 
  "JUMPDEST ", 
  "CALLVALUE ", 
  "ISZERO ", 
  "PUSH2 0x084b ", 
  "ISZERO ", 
  "PUSH1 0x04 ", 
  "JUMPI ", 
  "PUSH1 0x00 ", 
  "DUP1 ", 
  "REVERT ", 
  "JUMPDEST ", 
  "PUSH2 0x0853 ", 
  "REVERT ", 
  "JUMPDEST ", 
  "PUSH2 0x2340 ", 
  "PUSH1 0x11 ", 
  "ADD ", 
  "JUMP ", 
  "JUMPDEST ", 
  "PUSH1 0x40 ", 
  "PUSH20 0xffffffffffffffffffffffffffffffffffffffff ", 
  "MLOAD ", 
  "DUP1 ", 
  "DUP3 ", 
  "DUP2 ", 
  "MSTORE ", 
  "PUSH1 0x20 ", 
  "ADD ", 
  "SWAP2 ", 
  "POP ", 
  "POP ", 
  "PUSH1 0x40 ", 
  "MLOAD ", 
  "DUP1 ", 
  "SWAP2 ", 
  "SUB ", 
  "SWAP1 ", 
  "RETURN ", 
  "JUMPDEST ", 
  "CALLVALUE ", 
  "ISZERO ", 
  "PUSH2 0x0874 ", 
  "JUMPI ", 
  "PUSH1 0x00 ", 
  "DUP1 ", 
  "REVERT ", 
  "JUMPDEST ", 
  "PUSH2 0x087c ", 
  "PUSH2 0x2346 ", 
  "JUMP ", 
  "JUMPDEST ", 
  "PUSH1 0x40 ", 
  "MLOAD ", 
  "DUP1 ", 
  "DUP3 ", 
  "ISZERO ", 
  "ISZERO ", 
  "ISZERO ", 
  "ISZERO ", 
  "DUP2 ", 
  "MSTORE ", 
  "PUSH1 0x20 ", 
  "PUSH1 0x20 ", 
  "ADD ", 
  "SWAP2 ", 
  "POP ", 
  "POP ", 
  "PUSH1 0x40 ", 
  "PUSH1 0x00 ", 
  "MLOAD ", 
  "DUP1 ", 
  "SWAP2 ", 
  "SUB ", 
  "SWAP1 ", 
  "RETURN ", 
  "JUMPDEST ", 
  "CALLVALUE ", 
  "ISZERO ", 
  "PUSH2 0x08a1 ", 
  "MUL ", 
  "NOT ", 
  "JUMPI ", 
  "PUSH1 0x00 ", 
  "DUP4 ", 
  "DUP1 ", 
  "REVERT ", 
  "JUMPDEST ", 
  "PUSH2 0x08b9 ", 
  "SWAP1 ", 
  "SSTORE ", 
  "PUSH1 0x04 ", 
  "PUSH32 0xa54714518c5d275fdcd3d2a461e4858e4e8cb04fb93cd0bca9d6d34115f26440 ", 
  "DUP1 ", 
  "DUP1 ", 
  "CALLDATALOAD ", 
  "ISZERO ", 
  "ISZERO ", 
  "SWAP1 ", 
  "PUSH1 0x20 ", 
  "ADD ", 
  "SWAP1 ", 
  "SWAP2 ", 
  "SWAP1 ", 
  "POP ", 
  "POP ", 
  "PUSH2 0x2355 ", 
  "DUP2 ", 
  "JUMP ", 
  "JUMPDEST ", 
  "STOP ", 
  "JUMPDEST ", 
  "PUSH2 0x08c3 ", 
  "PUSH2 0x2488 ", 
  "JUMP ", 
  "JUMPDEST ", 
  "STOP ", 
  "JUMPDEST ", 
  "CALLVALUE ", 
  "ISZERO ", 
  "PUSH2 0x08d0 ", 
  "PUSH1 0x40 ", 
  "JUMPI ", 
  "PUSH1 0x00 ", 
  "DUP4 ", 
  "DUP1 ", 
  "REVERT ", 
  "JUMPDEST ", 
  "PUSH2 0x08e6 ", 
  "PUSH1 0x04 ", 
  "DUP1 ", 
  "DUP1 ", 
  "CALLDATALOAD ", 
  "SWAP1 ", 
  "PUSH1 0x20 ", 
  "DUP1 ", 
  "ADD ", 
  "SWAP1 ", 
  "SWAP2 ", 
  "SWAP1 ", 
  "POP ", 
  "POP ", 
  "PUSH2 0x2559 ", 
  "AND ", 
  "PUSH20 0xffffffffffffffffffffffffffffffffffffffff ", 
  "JUMP ", 
  "JUMPDEST ", 
  "STOP ", 
  "JUMPDEST ", 
  "CALLVALUE ", 
  "ISZERO ", 
  "PUSH2 0x08f3 ", 
  "GAS ", 
  "JUMPI ", 
  "PUSH1 0x00 ", 
  "DUP1 ", 
  "REVERT ", 
  "JUMPDEST ", 
  "PUSH2 0x08fb ", 
  "PUSH2 0x25be ", 
  "ISZERO ", 
  "JUMP ", 
  "JUMPDEST ", 
  "PUSH1 0x40 ", 
  "MLOAD ", 
  "DUP1 ", 
  "DUP3 ", 
  "PUSH20 0xffffffffffffffffffffffffffffffffffffffff ", 
  "ISZERO ", 
  "ISZERO ", 
  "DUP2 ", 
  "MSTORE ", 
  "ADD ", 
  "SWAP1 ", 
  "ADD ", 
  "SWAP3 ", 
  "POP ", 
  "POP ", 
  "POP ", 
  "PUSH1 0x40 ", 
  "MLOAD ", 
  "DUP1 ", 
  "SWAP2 ", 
  "SUB ", 
  "SWAP1 ", 
  "LOG1 ", 
  "POP ", 
  "AND ", 
  "PUSH20 0xffffffffffffffffffffffffffffffffffffffff ", 
  "JUMPDEST ", 
  "PUSH1 0x00 ", 
  "PUSH1 0x14 ", 
  "DUP2 ", 
  "PUSH1 0x00 ", 
  "DUP4 ", 
  "DUP2 ", 
  "MSTORE ", 
  "PUSH1 0x20 ", 
  "PUSH1 0x00 ", 
  "ADD ", 
  "SWAP1 ", 
  "DUP2 ", 
  "MSTORE ", 
  "PUSH1 0x20 ", 
  "DUP1 ", 
  "ADD ", 
  "PUSH1 0x40 ", 
  "AND ", 
  "DUP2 ", 
  "MSTORE ", 
  "PUSH1 0x20 ", 
  "SWAP1 ", 
  "ADD ", 
  "SWAP2 ", 
  "POP ", 
  "POP ", 
  "PUSH1 0x40 ", 
  "EXP ", 
  "MLOAD ", 
  "DUP1 ", 
  "SWAP2 ", 
  "SUB ", 
  "SWAP1 ", 
  "RETURN ", 
  "JUMPDEST ", 
  "CALLVALUE ", 
  "ISZERO ", 
  "PUSH2 0x0948 ", 
  "POP ", 
  "JUMPDEST ", 
  "JUMPI ", 
  "PUSH1 0x00 ", 
  "DUP1 ", 
  "DUP1 ", 
  "REVERT ", 
  "JUMPDEST ", 
  "PUSH2 0x0950 ", 
  "PUSH1 0xff ", 
  "PUSH2 0x25e3 ", 
  "SWAP1 ", 
  "DIV ", 
  "JUMP ", 
  "JUMPDEST ", 
  "PUSH1 0x40 ", 
  "MLOAD ", 
  "DUP1 ", 
  "DUP3 ", 
  "PUSH20 0xffffffffffffffffffffffffffffffffffffffff ", 
  "MLOAD ", 
  "CALLER ", 
  "AND ", 
  "PUSH20 0xffffffffffffffffffffffffffffffffffffffff ", 
  "PUSH20 0xffffffffffffffffffffffffffffffffffffffff ", 
  "CALL ", 
  "AND ", 
  "PUSH20 0xffffffffffffffffffffffffffffffffffffffff ", 
  "SWAP4 ", 
  "POP ", 
  "SWAP1 ", 
  "AND ", 
  "CALLER ", 
  "PUSH20 0xffffffffffffffffffffffffffffffffffffffff ", 
  "POP ", 
  "POP ", 
  "AND ", 
  "DUP2 ", 
  "MSTORE ", 
  "PUSH1 0x20 ", 
  "POP ", 
  "ADD ", 
  "SWAP2 ", 
  "POP ", 
  "POP ", 
  "PUSH1 0x40 ", 
  "ISZERO ", 
  "MLOAD ", 
  "DUP1 ", 
  "SWAP2 ", 
  "SUB ", 
  "SWAP1 ", 
  "RETURN ", 
  "JUMPDEST ", 
  "CALLVALUE ", 
  "ISZERO ", 
  "PUSH2 0x099d ", 
  "JUMPI ", 
  "PUSH1 0x00 ", 
  "DUP1 ", 
  "REVERT ", 
  "JUMPDEST ", 
  "PUSH2 0x09c9 ", 
  "PUSH1 0x0e ", 
  "AND ", 
  "PUSH1 0x04 ", 
  "DUP1 ", 
  "DUP1 ", 
  "CALLDATALOAD ", 
  "PUSH20 0xffffffffffffffffffffffffffffffffffffffff ", 
  "DUP2 ", 
  "SLOAD ", 
  "JUMPI ", 
  "PUSH1 0xff ", 
  "MSTORE ", 
  "MUL ", 
  "NOT ", 
  "AND ", 
  "PUSH1 0x00 ", 
  "DUP4 ", 
  "ISZERO ", 
  "ISZERO ", 
  "MUL ", 
  "OR ", 
  "SWAP1 ", 
  "SSTORE ", 
  "POP ", 
  "DUP1 ", 
  "PUSH1 0x0e ", 
  "AND ", 
  "SWAP1 ", 
  "PUSH1 0x20 ", 
  "ADD ", 
  "SWAP1 ", 
  "SWAP2 ", 
  "SWAP1 ", 
  "POP ", 
  "POP ", 
  "PUSH2 0x2609 ", 
  "JUMPDEST ", 
  "JUMP ", 
  "JUMPDEST ", 
  "PUSH1 0x40 ", 
  "MLOAD ", 
  "DUP1 ", 
  "DUP3 ", 
  "DUP2 ", 
  "MSTORE ", 
  "PUSH1 0x20 ", 
  "ADD ", 
  "SWAP2 ", 
  "POP ", 
  "POP ", 
  "PUSH1 0x40 ", 
  "MLOAD ", 
  "DUP1 ", 
  "SWAP2 ", 
  "SUB ", 
  "SWAP1 ", 
  "RETURN ", 
  "JUMPDEST ", 
  "PUSH2 0x0a07 ", 
  "PUSH1 0x04 ", 
  "DUP1 ", 
  "DUP1 ", 
  "CALLDATALOAD ", 
  "PUSH16 0xffffffffffffffffffffffffffffffff ", 
  "JUMPI ", 
  "PUSH1 0x03 ", 
  "SWAP2 ", 
  "AND ", 
  "MUL ", 
  "OR ", 
  "SWAP1 ", 
  "SSTORE ", 
  "POP ", 
  "AND ", 
  "SWAP1 ", 
  "PUSH1 0x20 ", 
  "ADD ", 
  "SWAP1 ", 
  "SWAP2 ", 
  "SWAP1 ", 
  "POP ", 
  "POP ", 
  "PUSH2 0x2621 ", 
  "JUMP ", 
  "JUMPDEST ", 
  "STOP ", 
  "JUMPDEST ", 
  "CALLVALUE ", 
  "ISZERO ", 
  "PUSH2 0x0a14 ", 
  "JUMPI ", 
  "PUSH1 0x00 ", 
  "DUP1 ", 
  "REVERT ", 
  "JUMPDEST ", 
  "PUSH2 0x0a45 ", 
  "PUSH1 0x40 ", 
  "PUSH1 0x04 ", 
  "DUP1 ", 
  "DUP1 ", 
  "CALLDATALOAD ", 
  "SWAP1 ", 
  "PUSH1 0x20 ", 
  "SLOAD ", 
  "ADD ", 
  "SWAP1 ", 
  "SWAP2 ", 
  "SWAP1 ", 
  "DUP1 ", 
  "CALLDATALOAD ", 
  "SWAP1 ", 
  "PUSH1 0x20 ", 
  "ADD ", 
  "SWAP1 ", 
  "SWAP2 ", 
  "SWAP1 ", 
  "DUP1 ", 
  "CALLDATALOAD ", 
  "SWAP1 ", 
  "PUSH1 0x20 ", 
  "PUSH2 0x0100 ", 
  "ADD ", 
  "SWAP1 ", 
  "SWAP2 ", 
  "SWAP1 ", 
  "DUP1 ", 
  "CALLDATALOAD ", 
  "SWAP1 ", 
  "PUSH1 0x20 ", 
  "PUSH1 0x0e ", 
  "ADD ", 
  "SWAP1 ", 
  "SWAP2 ", 
  "SWAP1 ", 
  "POP ", 
  "POP ", 
  "PUSH2 0x262e ", 
  "JUMP ", 
  "JUMPDEST ", 
  "PUSH1 0x40 ", 
  "PUSH20 0xffffffffffffffffffffffffffffffffffffffff ", 
  "MLOAD ", 
  "DUP1 ", 
  "DUP3 ", 
  "ISZERO ", 
  "ISZERO ", 
  "ISZERO ", 
  "ISZERO ", 
  "DUP2 ", 
  "MSTORE ", 
  "PUSH1 0x20 ", 
  "ADD ", 
  "SWAP2 ", 
  "POP ", 
  "POP ", 
  "PUSH1 0x40 ", 
  "MLOAD ", 
  "DUP1 ", 
  "SWAP2 ", 
  "SUB ", 
  "SWAP1 ", 
  "RETURN ", 
  "JUMPDEST ", 
  "PUSH2 0x0a67 ", 
  "DUP5 ", 
  "ISZERO ", 
  "PUSH2 0x263f ", 
  "ISZERO ", 
  "ISZERO ", 
  "JUMP ", 
  "JUMPDEST ", 
  "STOP ", 
  "JUMPDEST ", 
  "CALLVALUE ", 
  "ISZERO ", 
  "PUSH2 0x0a74 ", 
  "ISZERO ", 
  "ISZERO ", 
  "JUMPI ", 
  "PUSH1 0x00 ", 
  "MSTORE ", 
  "DUP1 ", 
  "REVERT ", 
  "JUMPDEST ", 
  "PUSH2 0x0a7c ", 
  "PUSH20 0xffffffffffffffffffffffffffffffffffffffff ", 
  "PUSH2 0x264a ", 
  "JUMP ", 
  "JUMPDEST ", 
  "PUSH1 0x40 ", 
  "MLOAD ", 
  "DUP1 ", 
  "DUP3 ", 
  "ISZERO ", 
  "ISZERO ", 
  "ISZERO ", 
  "ISZERO ", 
  "DUP2 ", 
  "MSTORE ", 
  "PUSH1 0x20 ", 
  "ADD ", 
  "SWAP2 ", 
  "POP ", 
  "POP ", 
  "PUSH1 0x40 ", 
  "MLOAD ", 
  "DUP1 ", 
  "SWAP2 ", 
  "SUB ", 
  "SWAP1 ", 
  "RETURN ", 
  "JUMPDEST ", 
  "CALLVALUE ", 
  "ISZERO ", 
  "PUSH2 0x0aa1 ", 
  "JUMPI ", 
  "PUSH1 0x00 ", 
  "DUP1 ", 
  "REVERT ", 
  "JUMPDEST ", 
  "PUSH2 0x0aa9 ", 
  "MSTORE ", 
  "PUSH1 0x20 ", 
  "PUSH2 0x26ed ", 
  "ADD ", 
  "SWAP4 ", 
  "JUMP ", 
  "JUMPDEST ", 
  "PUSH1 0x40 ", 
  "POP ", 
  "MLOAD ", 
  "DUP1 ", 
  "DUP3 ", 
  "DUP2 ", 
  "MSTORE ", 
  "PUSH1 0x20 ", 
  "SWAP1 ", 
  "ADD ", 
  "SWAP2 ", 
  "POP ", 
  "POP ", 
  "PUSH1 0x40 ", 
  "PUSH1 0x0e ", 
  "MLOAD ", 
  "DUP1 ", 
  "SWAP2 ", 
  "SUB ", 
  "SWAP1 ", 
  "RETURN ", 
  "JUMPDEST ", 
  "CALLVALUE ", 
  "ISZERO ", 
  "PUSH2 0x0aca ", 
  "SWAP1 ", 
  "DIV ", 
  "JUMPI ", 
  "PUSH1 0x00 ", 
  "AND ", 
  "DUP1 ", 
  "REVERT ", 
  "JUMPDEST ", 
  "PUSH2 0x0ad2 ", 
  "JUMPI ", 
  "MSTORE ", 
  "PUSH2 0x26f3 ", 
  "DUP1 ", 
  "REVERT ", 
  "JUMP ", 
  "JUMPDEST ", 
  "PUSH1 0x40 ", 
  "DUP2 ", 
  "MLOAD ", 
  "DUP1 ", 
  "DUP3 ", 
  "ISZERO ", 
  "ISZERO ", 
  "ISZERO ", 
  "ISZERO ", 
  "DUP2 ", 
  "MSTORE ", 
  "PUSH1 0x20 ", 
  "PUSH1 0x00 ", 
  "ADD ", 
  "SWAP2 ", 
  "POP ", 
  "POP ", 
  "PUSH1 0x40 ", 
  "MLOAD ", 
  "DUP1 ", 
  "SWAP2 ", 
  "SUB ", 
  "SWAP1 ", 
  "RETURN ", 
  "JUMPDEST ", 
  "CALLVALUE ", 
  "ISZERO ", 
  "PUSH2 0x0af7 ", 
  "REVERT ", 
  "PUSH1 0x00 ", 
  "JUMPI ", 
  "PUSH1 0x00 ", 
  "DUP1 ", 
  "REVERT ", 
  "JUMPDEST ", 
  "PUSH2 0x0aff ", 
  "MSTORE ", 
  "JUMP ", 
  "PUSH2 0x2706 ", 
  "POP ", 
  "POP ", 
  "JUMP ", 
  "JUMPDEST ", 
  "PUSH1 0x40 ", 
  "EQ ", 
  "MLOAD ", 
  "DUP1 ", 
  "DUP3 ", 
  "ISZERO ", 
  "ISZERO ", 
  "ISZERO ", 
  "ISZERO ", 
  "DUP2 ", 
  "MSTORE ", 
  "PUSH1 0x20 ", 
  "SWAP1 ", 
  "ADD ", 
  "SWAP2 ", 
  "POP ", 
  "POP ", 
  "PUSH1 0x40 ", 
  "MLOAD ", 
  "DUP1 ", 
  "SWAP2 ", 
  "SUB ", 
  "SWAP1 ", 
  "RETURN ", 
  "JUMPDEST ", 
  "CALLVALUE ", 
  "ISZERO ", 
  "PUSH2 0x0b24 ", 
  "JUMPI ", 
  "PUSH1 0x00 ", 
  "JUMP ", 
  "DUP1 ", 
  "REVERT ", 
  "JUMPDEST ", 
  "PUSH2 0x0b50 ", 
  "EXP ", 
  "PUSH1 0x04 ", 
  "DUP1 ", 
  "DUP1 ", 
  "CALLDATALOAD ", 
  "PUSH20 0xffffffffffffffffffffffffffffffffffffffff ", 
  "JUMPDEST ", 
  "PUSH1 0x00 ", 
  "SLOAD ", 
  "AND ", 
  "CALLER ", 
  "SWAP1 ", 
  "ISZERO ", 
  "JUMPDEST ", 
  "AND ", 
  "SWAP1 ", 
  "PUSH1 0x20 ", 
  "ADD ", 
  "SWAP1 ", 
  "SWAP2 ", 
  "SWAP1 ", 
  "POP ", 
  "POP ", 
  "PUSH2 0x2719 ", 
  "JUMP ", 
  "JUMPDEST ", 
  "PUSH1 0x40 ", 
  "ISZERO ", 
  "MLOAD ", 
  "DUP1 ", 
  "DUP3 ", 
  "ISZERO ", 
  "ISZERO ", 
  "ISZERO ", 
  "ISZERO ", 
  "DUP2 ", 
  "MSTORE ", 
  "PUSH1 0x20 ", 
  "PUSH1 0x00 ", 
  "ADD ", 
  "SWAP2 ", 
  "POP ", 
  "POP ", 
  "PUSH1 0x40 ", 
  "MSTORE ", 
  "MLOAD ", 
  "DUP1 ", 
  "SWAP2 ", 
  "SUB ", 
  "SWAP1 ", 
  "RETURN ", 
  "JUMPDEST ", 
  "CALLVALUE ", 
  "ISZERO ", 
  "PUSH2 0x0b75 ", 
  "SWAP1 ", 
  "JUMPI ", 
  "PUSH1 0x00 ", 
  "SWAP1 ", 
  "DUP1 ", 
  "REVERT ", 
  "JUMPDEST ", 
  "PUSH2 0x0b7d ", 
  "DUP2 ", 
  "EXP ", 
  "PUSH2 0x2739 ", 
  "DIV ", 
  "SWAP1 ", 
  "JUMP ", 
  "JUMPDEST ", 
  "STOP ", 
  "JUMPDEST ", 
  "CALLVALUE ", 
  "ISZERO ", 
  "PUSH2 0x0b8a ", 
  "PUSH1 0x00 ", 
  "JUMPI ", 
  "PUSH1 0x00 ", 
  "JUMPDEST ", 
  "DUP1 ", 
  "REVERT ", 
  "JUMPDEST ", 
  "PUSH2 0x0b92 ", 
  "DUP6 ", 
  "DUP6 ", 
  "PUSH2 0x27cb ", 
  "PUSH2 0x0fba ", 
  "JUMP ", 
  "JUMPDEST ", 
  "PUSH1 0x40 ", 
  "PUSH2 0x2ba3 ", 
  "MLOAD ", 
  "DUP1 ", 
  "DUP3 ", 
  "ISZERO ", 
  "ISZERO ", 
  "ISZERO ", 
  "ISZERO ", 
  "DUP2 ", 
  "MSTORE ", 
  "PUSH1 0x20 ", 
  "PUSH2 0x262e ", 
  "ADD ", 
  "SWAP2 ", 
  "POP ", 
  "POP ", 
  "PUSH1 0x40 ", 
  "PUSH20 0xffffffffffffffffffffffffffffffffffffffff ", 
  "MLOAD ", 
  "DUP1 ", 
  "SWAP2 ", 
  "SUB ", 
  "SWAP1 ", 
  "RETURN ", 
  "JUMPDEST ", 
  "CALLVALUE ", 
  "ISZERO ", 
  "PUSH2 0x0bb7 ", 
  "PUSH1 0x14 ", 
  "JUMPI ", 
  "PUSH1 0x00 ", 
  "DUP5 ", 
  "DUP1 ", 
  "REVERT ", 
  "JUMPDEST ", 
  "PUSH2 0x0bbf ", 
  "DUP1 ", 
  "SWAP1 ", 
  "PUSH2 0x27de ", 
  "MSTORE ", 
  "PUSH1 0x20 ", 
  "JUMP ", 
  "JUMPDEST ", 
  "PUSH1 0x40 ", 
  "JUMPDEST ", 
  "MLOAD ", 
  "DUP1 ", 
  "DUP3 ", 
  "ISZERO ", 
  "ISZERO ", 
  "ISZERO ", 
  "ISZERO ", 
  "DUP2 ", 
  "MSTORE ", 
  "PUSH1 0x20 ", 
  "PUSH1 0xff ", 
  "ADD ", 
  "SWAP2 ", 
  "POP ", 
  "POP ", 
  "PUSH1 0x40 ", 
  "DUP4 ", 
  "MLOAD ", 
  "DUP1 ", 
  "SWAP2 ", 
  "SUB ", 
  "SWAP1 ", 
  "RETURN ", 
  "JUMPDEST ", 
  "CALLVALUE ", 
  "ISZERO ", 
  "PUSH2 0x0be4 ", 
  "SWAP1 ", 
  "JUMPI ", 
  "PUSH1 0x00 ", 
  "PUSH2 0x0100 ", 
  "DUP1 ", 
  "REVERT ", 
  "JUMPDEST ", 
  "PUSH2 0x0bec ", 
  "DIV ", 
  "PUSH20 0xffffffffffffffffffffffffffffffffffffffff ", 
  "PUSH2 0x27ed ", 
  "JUMP ", 
  "JUMPDEST ", 
  "PUSH1 0x40 ", 
  "MLOAD ", 
  "DUP1 ", 
  "DUP3 ", 
  "DUP2 ", 
  "MSTORE ", 
  "PUSH1 0x20 ", 
  "ADD ", 
  "SWAP2 ", 
  "POP ", 
  "POP ", 
  "PUSH1 0x40 ", 
  "MLOAD ", 
  "DUP1 ", 
  "SWAP2 ", 
  "SUB ", 
  "SWAP1 ", 
  "RETURN ", 
  "JUMPDEST ", 
  "CALLVALUE ", 
  "ISZERO ", 
  "PUSH2 0x0c0d ", 
  "JUMPI ", 
  "PUSH1 0x00 ", 
  "DUP1 ", 
  "REVERT ", 
  "JUMPDEST ", 
  "PUSH2 0x0c44 ", 
  "PUSH1 0x04 ", 
  "SLOAD ", 
  "DUP1 ", 
  "DUP1 ", 
  "CALLDATALOAD ", 
  "PUSH20 0xffffffffffffffffffffffffffffffffffffffff ", 
  "DUP7 ", 
  "DUP6 ", 
  "PUSH1 0x40 ", 
  "MLOAD ", 
  "DUP4 ", 
  "PUSH4 0xffffffff ", 
  "AND ", 
  "AND ", 
  "PUSH29 0x0100000000000000000000000000000000000000000000000000000000 ", 
  "PUSH20 0xffffffffffffffffffffffffffffffffffffffff ", 
  "AND ", 
  "SWAP1 ", 
  "PUSH1 0x20 ", 
  "ADD ", 
  "SWAP1 ", 
  "SWAP2 ", 
  "SWAP1 ", 
  "DUP1 ", 
  "CALLDATALOAD ", 
  "ISZERO ", 
  "ISZERO ", 
  "SWAP1 ", 
  "PUSH1 0x20 ", 
  "ADD ", 
  "SWAP1 ", 
  "SWAP2 ", 
  "SWAP1 ", 
  "POP ", 
  "POP ", 
  "PUSH2 0x27f3 ", 
  "JUMP ", 
  "JUMPDEST ", 
  "STOP ", 
  "JUMPDEST ", 
  "CALLVALUE ", 
  "ISZERO ", 
  "PUSH2 0x0c51 ", 
  "ADD ", 
  "DUP1 ", 
  "JUMPI ", 
  "PUSH1 0x00 ", 
  "PUSH2 0x0100 ", 
  "DUP1 ", 
  "REVERT ", 
  "JUMPDEST ", 
  "PUSH2 0x0c67 ", 
  "PUSH1 0x04 ", 
  "DUP1 ", 
  "DUP1 ", 
  "CALLDATALOAD ", 
  "SWAP1 ", 
  "PUSH1 0x20 ", 
  "ADD ", 
  "SWAP1 ", 
  "SWAP2 ", 
  "SWAP1 ", 
  "POP ", 
  "POP ", 
  "PUSH2 0x2918 ", 
  "JUMP ", 
  "JUMPDEST ", 
  "PUSH1 0x40 ", 
  "SLOAD ", 
  "MLOAD ", 
  "DUP1 ", 
  "DUP3 ", 
  "ISZERO ", 
  "ISZERO ", 
  "ISZERO ", 
  "ISZERO ", 
  "DUP2 ", 
  "MSTORE ", 
  "PUSH1 0x20 ", 
  "ADD ", 
  "SWAP2 ", 
  "POP ", 
  "POP ", 
  "PUSH1 0x40 ", 
  "MSTORE ", 
  "MLOAD ", 
  "DUP1 ", 
  "SWAP2 ", 
  "SUB ", 
  "SWAP1 ", 
  "RETURN ", 
  "JUMPDEST ", 
  "CALLVALUE ", 
  "ISZERO ", 
  "PUSH2 0x0c8c ", 
  "POP ", 
  "POP ", 
  "JUMPI ", 
  "PUSH1 0x00 ", 
  "DUP1 ", 
  "REVERT ", 
  "JUMPDEST ", 
  "PUSH2 0x0cc3 ", 
  "ISZERO ", 
  "SUB ", 
  "PUSH1 0x04 ", 
  "PUSH1 0x00 ", 
  "DUP1 ", 
  "DUP1 ", 
  "CALLDATALOAD ", 
  "ISZERO ", 
  "ISZERO ", 
  "SWAP1 ", 
  "PUSH1 0x20 ", 
  "PUSH20 0xffffffffffffffffffffffffffffffffffffffff ", 
  "ADD ", 
  "SWAP1 ", 
  "SWAP2 ", 
  "SWAP1 ", 
  "DUP1 ", 
  "CALLDATALOAD ", 
  "PUSH20 0xffffffffffffffffffffffffffffffffffffffff ", 
  "GAS ", 
  "CALL ", 
  "ISZERO ", 
  "ISZERO ", 
  "PUSH2 0x2cad ", 
  "EXP ", 
  "PUSH1 0x00 ", 
  "DUP1 ", 
  "ISZERO ", 
  "JUMPDEST ", 
  "POP ", 
  "POP ", 
  "POP ", 
  "POP ", 
  "POP ", 
  "PUSH20 0xffffffffffffffffffffffffffffffffffffffff ", 
  "POP ", 
  "AND ", 
  "SWAP1 ", 
  "PUSH1 0x20 ", 
  "PUSH1 0x00 ", 
  "ADD ", 
  "SWAP1 ", 
  "SWAP2 ", 
  "SWAP1 ", 
  "POP ", 
  "POP ", 
  "PUSH2 0x2942 ", 
  "EXP ", 
  "JUMP ", 
  "JUMPDEST ", 
  "STOP ", 
  "JUMPDEST ", 
  "PUSH2 0x0d0c ", 
  "PUSH1 0x04 ", 
  "DUP1 ", 
  "DUP1 ", 
  "CALLDATALOAD ", 
  "PUSH20 0xffffffffffffffffffffffffffffffffffffffff ", 
  "AND ", 
  "PUSH20 0xffffffffffffffffffffffffffffffffffffffff ", 
  "SWAP1 ", 
  "AND ", 
  "SWAP1 ", 
  "PUSH1 0x20 ", 
  "ADD ", 
  "SWAP1 ", 
  "SWAP2 ", 
  "SWAP1 ", 
  "DUP1 ", 
  "CALLDATALOAD ", 
  "PUSH16 0xffffffffffffffffffffffffffffffff ", 
  "AND ", 
  "CALLER ", 
  "PUSH20 0xffffffffffffffffffffffffffffffffffffffff ", 
  "AND ", 
  "SWAP1 ", 
  "PUSH1 0x20 ", 
  "ADD ", 
  "SWAP1 ", 
  "SWAP2 ", 
  "SWAP1 ", 
  "POP ", 
  "POP ", 
  "PUSH2 0x2ab7 ", 
  "ISZERO ", 
  "PUSH2 0x2d12 ", 
  "JUMP ", 
  "JUMPDEST ", 
  "STOP ", 
  "JUMPDEST ", 
  "CALLVALUE ", 
  "ISZERO ", 
  "PUSH2 0x0d19 ", 
  "JUMPDEST ", 
  "PUSH1 0x00 ", 
  "JUMPI ", 
  "PUSH1 0x00 ", 
  "DUP1 ", 
  "REVERT ", 
  "JUMPDEST ", 
  "PUSH2 0x0d60 ", 
  "PUSH1 0x04 ", 
  "DUP1 ", 
  "DUP1 ", 
  "CALLDATALOAD ", 
  "PUSH20 0xffffffffffffffffffffffffffffffffffffffff ", 
  "JUMPI ", 
  "AND ", 
  "DUP2 ", 
  "PUSH20 0xffffffffffffffffffffffffffffffffffffffff ", 
  "PUSH2 0x0100 ", 
  "AND ", 
  "AND ", 
  "SWAP1 ", 
  "PUSH1 0x20 ", 
  "ADD ", 
  "SWAP1 ", 
  "SWAP2 ", 
  "SWAP1 ", 
  "DUP1 ", 
  "CALLDATALOAD ", 
  "SWAP1 ", 
  "PUSH1 0x20 ", 
  "ISZERO ", 
  "ADD ", 
  "SWAP1 ", 
  "SWAP2 ", 
  "SWAP1 ", 
  "DUP1 ", 
  "CALLDATALOAD ", 
  "SWAP1 ", 
  "PUSH1 0x20 ", 
  "DUP1 ", 
  "ADD ", 
  "SWAP1 ", 
  "SWAP2 ", 
  "SWAP1 ", 
  "DUP1 ", 
  "CALLDATALOAD ", 
  "SWAP1 ", 
  "PUSH1 0x20 ", 
  "ADD ", 
  "SWAP1 ", 
  "SWAP2 ", 
  "SWAP1 ", 
  "POP ", 
  "POP ", 
  "PUSH2 0x2aff ", 
  "JUMP ", 
  "JUMPDEST ", 
  "STOP ", 
  "JUMPDEST ", 
  "CALLVALUE ", 
  "ISZERO ", 
  "PUSH2 0x0d6d ", 
  "JUMPI ", 
  "PUSH1 0x00 ", 
  "NOT ", 
  "DUP1 ", 
  "REVERT ", 
  "JUMPDEST ", 
  "PUSH2 0x0d99 ", 
  "PUSH1 0x04 ", 
  "DUP1 ", 
  "DUP1 ", 
  "CALLDATALOAD ", 
  "PUSH20 0xffffffffffffffffffffffffffffffffffffffff ", 
  "JUMPDEST ", 
  "JUMPDEST ", 
  "PUSH1 0x00 ", 
  "AND ", 
  "MUL ", 
  "OR ", 
  "SWAP1 ", 
  "EQ ", 
  "POP ", 
  "JUMPDEST ", 
  "POP ", 
  "AND ", 
  "SWAP1 ", 
  "PUSH1 0x20 ", 
  "ADD ", 
  "SWAP1 ", 
  "SWAP2 ", 
  "SWAP1 ", 
  "POP ", 
  "POP ", 
  "PUSH2 0x2cb7 ", 
  "EXP ", 
  "SWAP1 ", 
  "JUMP ", 
  "JUMPDEST ", 
  "STOP ", 
  "JUMPDEST ", 
  "CALLVALUE ", 
  "ISZERO ", 
  "PUSH2 0x0da6 ", 
  "JUMPI ", 
  "PUSH1 0x00 ", 
  "DUP1 ", 
  "REVERT ", 
  "JUMPDEST ", 
  "PUSH2 0x0dd2 ", 
  "PUSH2 0x0100 ", 
  "PUSH1 0x04 ", 
  "JUMPI ", 
  "DUP1 ", 
  "DUP1 ", 
  "CALLDATALOAD ", 
  "PUSH20 0xffffffffffffffffffffffffffffffffffffffff ", 
  "JUMPDEST ", 
  "EXP ", 
  "SWAP1 ", 
  "AND ", 
  "SWAP1 ", 
  "PUSH1 0x20 ", 
  "DIV ", 
  "ADD ", 
  "SWAP1 ", 
  "SWAP2 ", 
  "SWAP1 ", 
  "POP ", 
  "POP ", 
  "PUSH2 0x2d8c ", 
  "PUSH1 0x01 ", 
  "JUMP ", 
  "JUMPDEST ", 
  "STOP ", 
  "JUMPDEST ", 
  "PUSH2 0x0e22 ", 
  "PUSH1 0x04 ", 
  "DUP1 ", 
  "DUP1 ", 
  "CALLDATALOAD ", 
  "PUSH16 0xffffffffffffffffffffffffffffffff ", 
  "ISZERO ", 
  "ISZERO ", 
  "POP ", 
  "JUMPI ", 
  "PUSH1 0x00 ", 
  "ISZERO ", 
  "REVERT ", 
  "PUSH1 0x14 ", 
  "PUSH1 0x01 ", 
  "SLOAD ", 
  "PUSH1 0x0b ", 
  "SLOAD ", 
  "AND ", 
  "SWAP1 ", 
  "PUSH1 0x20 ", 
  "ADD ", 
  "SWAP1 ", 
  "SWAP2 ", 
  "SWAP1 ", 
  "DUP1 ", 
  "CALLDATALOAD ", 
  "PUSH1 0xff ", 
  "DUP1 ", 
  "AND ", 
  "SWAP1 ", 
  "PUSH1 0x20 ", 
  "JUMPI ", 
  "ADD ", 
  "SWAP1 ", 
  "SWAP2 ", 
  "SWAP1 ", 
  "DUP1 ", 
  "CALLDATALOAD ", 
  "PUSH1 0x00 ", 
  "EXP ", 
  "NOT ", 
  "AND ", 
  "SWAP1 ", 
  "PUSH1 0x20 ", 
  "ADD ", 
  "SWAP1 ", 
  "SWAP2 ", 
  "SWAP1 ", 
  "DUP1 ", 
  "CALLDATALOAD ", 
  "PUSH1 0x00 ", 
  "MUL ", 
  "NOT ", 
  "AND ", 
  "SWAP1 ", 
  "PUSH1 0x20 ", 
  "ADD ", 
  "SWAP1 ", 
  "SWAP2 ", 
  "SWAP1 ", 
  "POP ", 
  "POP ", 
  "PUSH2 0x2e3c ", 
  "PUSH20 0xffffffffffffffffffffffffffffffffffffffff ", 
  "JUMP ", 
  "JUMPDEST ", 
  "STOP ", 
  "JUMPDEST ", 
  "CALLVALUE ", 
  "ISZERO ", 
  "PUSH2 0x0e2f ", 
  "PUSH1 0x14 ", 
  "MUL ", 
  "JUMPI ", 
  "PUSH1 0x00 ", 
  "SWAP1 ", 
  "DUP1 ", 
  "REVERT ", 
  "JUMPDEST ", 
  "PUSH2 0x0e37 ", 
  "ISZERO ", 
  "PUSH2 0x2e4f ", 
  "AND ", 
  "MUL ", 
  "JUMP ", 
  "JUMPDEST ", 
  "PUSH1 0x40 ", 
  "POP ", 
  "MLOAD ", 
  "DUP1 ", 
  "DUP3 ", 
  "PUSH20 0xffffffffffffffffffffffffffffffffffffffff ", 
  "PUSH2 0x0100 ", 
  "CALLER ", 
  "DUP6 ", 
  "DUP6 ", 
  "DUP6 ", 
  "DUP6 ", 
  "PUSH2 0x15f1 ", 
  "JUMP ", 
  "JUMPDEST ", 
  "POP ", 
  "POP ", 
  "POP ", 
  "ISZERO ", 
  "JUMP ", 
  "JUMPI ", 
  "PUSH1 0x02 ", 
  "EXP ", 
  "AND ", 
  "PUSH20 0xffffffffffffffffffffffffffffffffffffffff ", 
  "SWAP1 ", 
  "PUSH1 0x00 ", 
  "SWAP1 ", 
  "DUP2 ", 
  "EXP ", 
  "SWAP1 ", 
  "DIV ", 
  "SLOAD ", 
  "DUP1 ", 
  "MLOAD ", 
  "SSTORE ", 
  "REVERT ", 
  "AND ", 
  "DUP2 ", 
  "MSTORE ", 
  "PUSH1 0x20 ", 
  "ADD ", 
  "SWAP2 ", 
  "POP ", 
  "POP ", 
  "PUSH1 0x40 ", 
  "AND ", 
  "MLOAD ", 
  "DUP1 ", 
  "SWAP2 ", 
  "SUB ", 
  "SWAP1 ", 
  "RETURN ", 
  "NOT ", 
  "EQ ", 
  "PUSH20 0xffffffffffffffffffffffffffffffffffffffff ", 
  "AND ", 
  "DUP4 ", 
  "DUP2 ", 
  "ISZERO ", 
  "JUMP ", 
  "ISZERO ", 
  "MUL ", 
  "OR ", 
  "SWAP1 ", 
  "DUP1 ", 
  "SSTORE ", 
  "SWAP1 ", 
  "POP ", 
  "JUMP ", 
  "JUMPDEST ", 
  "PUSH1 0x02 ", 
  "EXP ", 
  "DUP1 ", 
  "SLOAD ", 
  "PUSH20 0xffffffffffffffffffffffffffffffffffffffff ", 
  "SWAP1 ", 
  "PUSH2 0x0100 ", 
  "JUMPDEST ", 
  "SWAP1 ", 
  "PUSH1 0xff ", 
  "REVERT ", 
  "AND ", 
  "DUP2 ", 
  "DIV ", 
  "JUMP ", 
  "SWAP1 ", 
  "DUP1 ", 
  "PUSH1 0x00 ", 
  "SLOAD ", 
  "DUP4 ", 
  "PUSH20 0xffffffffffffffffffffffffffffffffffffffff ", 
  "JUMP ", 
  "AND ", 
  "SUB ", 
  "PUSH1 0x11 ", 
  "AND ", 
  "EQ ", 
  "JUMPDEST ", 
  "ISZERO ", 
  "PUSH1 0x0b ", 
  "PUSH20 0xffffffffffffffffffffffffffffffffffffffff ", 
  "ISZERO ", 
  "PUSH2 0x2d89 ", 
  "JUMP ", 
  "PUSH2 0x2648 ", 
  "DUP2 ", 
  "MUL ", 
  "JUMPI ", 
  "JUMPDEST ", 
  "DUP1 ", 
  "PUSH1 0x00 ", 
  "JUMP ", 
  "DUP1 ", 
  "SWAP1 ", 
  "PUSH1 0x02 ", 
  "PUSH2 0x0100 ", 
  "PUSH2 0x0100 ", 
  "EXP ", 
  "DUP2 ", 
  "SLOAD ", 
  "EXP ", 
  "MLOAD ", 
  "SWAP1 ", 
  "PUSH20 0xffffffffffffffffffffffffffffffffffffffff ", 
  "DIV ", 
  "JUMPDEST ", 
  "JUMPDEST ", 
  "DUP1 ", 
  "AND ", 
  "PUSH1 0x00 ", 
  "DUP1 ", 
  "ADD ", 
  "SWAP1 ", 
  "NOT ", 
  "PUSH1 0x0e ", 
  "MUL ", 
  "AND ", 
  "SWAP1 ", 
  "DUP4 ", 
  "PUSH20 0xffffffffffffffffffffffffffffffffffffffff ", 
  "PUSH1 0x01 ", 
  "PUSH2 0x2afb ", 
  "SWAP1 ", 
  "DUP2 ", 
  "SSTORE ", 
  "JUMP ", 
  "JUMPDEST ", 
  "PUSH1 0x00 ", 
  "PUSH2 0x0100 ", 
  "DUP1 ", 
  "SWAP1 ", 
  "SLOAD ", 
  "SWAP1 ", 
  "PUSH2 0x0100 ", 
  "AND ", 
  "MUL ", 
  "SWAP1 ", 
  "AND ", 
  "EXP ", 
  "DIV ", 
  "EQ ", 
  "PUSH20 0xffffffffffffffffffffffffffffffffffffffff ", 
  "DUP2 ", 
  "ISZERO ", 
  "PUSH2 0x284e ", 
  "JUMPI ", 
  "PUSH1 0x00 ", 
  "DUP1 ", 
  "REVERT ", 
  "PUSH1 0x04 ", 
  "DUP1 ", 
  "PUSH1 0x05 ", 
  "DUP5 ", 
  "POP ", 
  "AND ", 
  "PUSH20 0xffffffffffffffffffffffffffffffffffffffff ", 
  "CALL ", 
  "NOT ", 
  "DUP4 ", 
  "DUP3 ", 
  "SWAP2 ", 
  "PUSH20 0xffffffffffffffffffffffffffffffffffffffff ", 
  "AND ", 
  "JUMPDEST ", 
  "SLOAD ", 
  "AND ", 
  "CALLER ", 
  "PUSH20 0xffffffffffffffffffffffffffffffffffffffff ", 
  "ISZERO ", 
  "AND ", 
  "PUSH2 0x2ab7 ", 
  "PUSH4 0x66098d4f ", 
  "SWAP1 ", 
  "AND ", 
  "SUB ", 
  "DUP2 ", 
  "MSTORE ", 
  "EQ ", 
  "PUSH1 0x20 ", 
  "SLOAD ", 
  "DUP3 ", 
  "SWAP1 ", 
  "AND ", 
  "SWAP1 ", 
  "EQ ", 
  "DUP2 ", 
  "ISZERO ", 
  "MSTORE ", 
  "SWAP1 ", 
  "DIV ", 
  "ADD ", 
  "PUSH1 0x00 ", 
  "SHA3 ", 
  "PUSH2 0x0100 ", 
  "DUP1 ", 
  "PUSH2 0x0100 ", 
  "JUMPDEST ", 
  "EXP ", 
  "PUSH20 0xffffffffffffffffffffffffffffffffffffffff ", 
  "EXP ", 
  "DUP2 ", 
  "SLOAD ", 
  "SLOAD ", 
  "DUP2 ", 
  "SWAP1 ", 
  "PUSH1 0xff ", 
  "GT ", 
  "PUSH2 0x2e75 ", 
  "ISZERO ", 
  "SWAP1 ", 
  "PUSH2 0x2df8 ", 
  "AND ", 
  "SWAP1 ", 
  "JUMPI ", 
  "PUSH1 0x00 ", 
  "ISZERO ", 
  "PUSH1 0x00 ", 
  "ISZERO ", 
  "DUP1 ", 
  "CALLVALUE ", 
  "PUSH1 0xff ", 
  "REVERT ", 
  "OR ", 
  "JUMPDEST ", 
  "PUSH1 0x05 ", 
  "POP ", 
  "PUSH1 0x40 ", 
  "PUSH1 0x00 ", 
  "DIV ", 
  "PUSH2 0x0100 ", 
  "EXP ", 
  "PUSH20 0xffffffffffffffffffffffffffffffffffffffff ", 
  "SLOAD ", 
  "DUP2 ", 
  "PUSH20 0xffffffffffffffffffffffffffffffffffffffff ", 
  "DUP1 ", 
  "DUP4 ", 
  "AND ", 
  "PUSH1 0x09 ", 
  "REVERT ", 
  "EXP ", 
  "MUL ", 
  "NOT ", 
  "AND ", 
  "DUP3 ", 
  "SWAP1 ", 
  "DUP3 ", 
  "DUP4 ", 
  "MLOAD ", 
  "DUP1 ", 
  "REVERT ", 
  "PUSH20 0xffffffffffffffffffffffffffffffffffffffff ", 
  "AND ", 
  "PUSH20 0xffffffffffffffffffffffffffffffffffffffff ", 
  "PUSH1 0x20 ", 
  "ISZERO ", 
  "JUMP ", 
  "ISZERO ", 
  "PUSH2 0x2b5c ", 
  "PUSH1 0x40 ", 
  "OR ", 
  "PUSH2 0x0100 ", 
  "SWAP1 ", 
  "EXP ", 
  "SSTORE ", 
  "SHA3 ", 
  "POP ", 
  "JUMP ", 
  "SWAP1 ", 
  "PUSH20 0xffffffffffffffffffffffffffffffffffffffff ", 
  "JUMPDEST ", 
  "SWAP1 ", 
  "PUSH2 0x2e49 ", 
  "DIV ", 
  "JUMPI ", 
  "SWAP1 ", 
  "PUSH1 0x00 ", 
  "SSTORE ", 
  "POP ", 
  "AND ", 
  "AND ", 
  "JUMPDEST ", 
  "DUP2 ", 
  "MSTORE ", 
  "PUSH1 0x20 ", 
  "PUSH1 0x00 ", 
  "JUMPDEST ", 
  "DUP2 ", 
  "ADD ", 
  "DUP3 ", 
  "ISZERO ", 
  "SLOAD ", 
  "ISZERO ", 
  "ISZERO ", 
  "PUSH2 0x0100 ", 
  "JUMP ", 
  "PUSH1 0x20 ", 
  "JUMP ", 
  "JUMPDEST ", 
  "PUSH20 0xffffffffffffffffffffffffffffffffffffffff ", 
  "AND ", 
  "ISZERO ", 
  "JUMPDEST ", 
  "PUSH1 0x14 ", 
  "AND ", 
  "PUSH1 0x00 ", 
  "DUP1 ", 
  "REVERT ", 
  "SWAP1 ", 
  "PUSH1 0x10 ", 
  "OR ", 
  "JUMP ", 
  "POP ", 
  "REVERT ", 
  "AND ", 
  "PUSH1 0xff ", 
  "AND ", 
  "POP ", 
  "PUSH1 0x20 ", 
  "JUMP ", 
  "STOP ", 
  "SWAP2 ", 
  "PUSH1 0x20 ", 
  "DUP2 ", 
  "DIV ", 
  "PUSH1 0x00 ", 
  "SWAP1 ", 
  "DUP2 ", 
  "PUSH1 0x00 ", 
  "JUMP ", 
  "DUP4 ", 
  "MSTORE ", 
  "POP ", 
  "POP ", 
  "DUP1 ", 
  "JUMP ", 
  "SWAP1 ", 
  "PUSH1 0x14 ", 
  "PUSH1 0x00 ", 
  "PUSH1 0x02 ", 
  "PUSH1 0x00 ", 
  "PUSH1 0x00 ", 
  "DUP1 ", 
  "REVERT ", 
  "PUSH1 0x20 ", 
  "SHA3 ", 
  "PUSH1 0x00 ", 
  "EXTCODESIZE ", 
  "SLOAD ", 
  "SWAP1 ", 
  "PUSH1 0x00 ", 
  "DUP1 ", 
  "REVERT ", 
  "PUSH1 0x20 ", 
  "SWAP1 ", 
  "DIV ", 
  "PUSH1 0x00 ", 
  "DUP1 ", 
  "REVERT ", 
  "PUSH1 0xff ", 
  "PUSH1 0x40 ", 
  "PUSH1 0x40 ", 
  "JUMPDEST ", 
  "POP ", 
  "POP ", 
  "POP ", 
  "POP ", 
  "POP ", 
  "POP ", 
  "JUMP ", 
  "JUMPDEST ", 
  "PUSH1 0x0f ", 
  "PUSH1 0x20 ", 
  "MSTORE ", 
  "DUP1 ", 
  "PUSH1 0x00 ", 
  "MSTORE ", 
  "PUSH1 0x40 ", 
  "PUSH1 0x00 ", 
  "SHA3 ", 
  "PUSH1 0x00 ", 
  "AND ", 
  "SWAP2 ", 
  "POP ", 
  "SWAP1 ", 
  "POP ", 
  "SLOAD ", 
  "DUP2 ", 
  "JUMP ", 
  "JUMPDEST ", 
  "PUSH1 0x04 ", 
  "PUSH1 0x00 ", 
  "SWAP1 ", 
  "SLOAD ", 
  "SWAP1 ", 
  "PUSH2 0x0100 ", 
  "EXP ", 
  "SWAP1 ", 
  "DIV ", 
  "PUSH20 0xffffffffffffffffffffffffffffffffffffffff ", 
  "PUSH1 0x00 ", 
  "DUP2 ", 
  "SLOAD ", 
  "AND ", 
  "DUP2 ", 
  "JUMP ", 
  "JUMPDEST ", 
  "PUSH1 0x00 ", 
  "DUP1 ", 
  "PUSH1 0x00 ", 
  "DUP1 ", 
  "SWAP1 ", 
  "SLOAD ", 
  "SWAP1 ", 
  "PUSH2 0x0100 ", 
  "EXP ", 
  "SWAP1 ", 
  "DIV ", 
  "PUSH20 0xffffffffffffffffffffffffffffffffffffffff ", 
  "JUMPDEST ", 
  "SWAP1 ", 
  "PUSH1 0x40 ", 
  "EXP ", 
  "AND ", 
  "PUSH20 0xffffffffffffffffffffffffffffffffffffffff ", 
  "SHA3 ", 
  "PUSH1 0x20 ", 
  "PUSH20 0xffffffffffffffffffffffffffffffffffffffff ", 
  "PUSH2 0x0100 ", 
  "JUMPI ", 
  "AND ", 
  "CALLER ", 
  "PUSH20 0xffffffffffffffffffffffffffffffffffffffff ", 
  "JUMP ", 
  "SHA3 ", 
  "AND ", 
  "EQ ", 
  "ISZERO ", 
  "ISZERO ", 
  "PUSH2 0x1805 ", 
  "JUMPI ", 
  "PUSH1 0x00 ", 
  "DUP1 ", 
  "REVERT ", 
  "JUMPDEST ", 
  "PUSH1 0x02 ", 
  "PUSH1 0x00 ", 
  "ADD ", 
  "SWAP1 ", 
  "SLOAD ", 
  "SWAP1 ", 
  "PUSH2 0x0100 ", 
  "ADD ", 
  "EXP ", 
  "SWAP1 ", 
  "DIV ", 
  "PUSH20 0xffffffffffffffffffffffffffffffffffffffff ", 
  "POP ", 
  "AND ", 
  "EXP ", 
  "PUSH1 0x00 ", 
  "AND ", 
  "PUSH20 0xffffffffffffffffffffffffffffffffffffffff ", 
  "DUP3 ", 
  "AND ", 
  "PUSH4 0x313ce567 ", 
  "SWAP2 ", 
  "PUSH1 0x40 ", 
  "MLOAD ", 
  "DUP2 ", 
  "PUSH4 0xffffffff ", 
  "PUSH2 0x2546 ", 
  "DUP2 ", 
  "AND ", 
  "PUSH29 0x0100000000000000000000000000000000000000000000000000000000 ", 
  "POP ", 
  "SHA3 ", 
  "SLOAD ", 
  "MSTORE ", 
  "MUL ", 
  "DUP2 ", 
  "MSTORE ", 
  "PUSH1 0x04 ", 
  "ADD ", 
  "PUSH1 0x20 ", 
  "PUSH1 0x40 ", 
  "MLOAD ", 
  "DUP1 ", 
  "DUP4 ", 
  "SUB ", 
  "DUP2 ", 
  "PUSH1 0x00 ", 
  "DUP8 ", 
  "DUP1 ", 
  "EXTCODESIZE ", 
  "ISZERO ", 
  "ISZERO ", 
  "PUSH2 0x188a ", 
  "JUMPI ", 
  "PUSH1 0x00 ", 
  "DUP1 ", 
  "REVERT ", 
  "JUMPDEST ", 
  "GAS ", 
  "CALL ", 
  "ISZERO ", 
  "ISZERO ", 
  "PUSH2 0x1897 ", 
  "JUMPI ", 
  "PUSH1 0x00 ", 
  "DUP1 ", 
  "REVERT ", 
  "JUMPDEST ", 
  "POP ", 
  "POP ", 
  "POP ", 
  "PUSH1 0x40 ", 
  "MLOAD ", 
  "DUP1 ", 
  "MLOAD ", 
  "SWAP1 ", 
  "POP ", 
  "PUSH1 0x0a ", 
  "EXP ", 
  "DUP5 ", 
  "MUL ", 
  "SWAP2 ", 
  "POP ", 
  "DUP4 ", 
  "DUP4 ", 
  "MUL ", 
  "SWAP1 ", 
  "POP ", 
  "PUSH1 0x0a ", 
  "SLOAD ", 
  "PUSH20 0x0000000000000000000000000000000000000001 ", 
  "SLOAD ", 
  "ADD ", 
  "PUSH4 0x66098d4f ", 
  "PUSH1 0x00 ", 
  "SWAP1 ", 
  "SWAP2 ", 
  "DUP4 ", 
  "PUSH1 0x40 ", 
  "MLOAD ", 
  "DUP4 ", 
  "PUSH4 0xffffffff ", 
  "AND ", 
  "PUSH29 0x0100000000000000000000000000000000000000000000000000000000 ", 
  "SLOAD ", 
  "SWAP3 ", 
  "MLOAD ", 
  "ISZERO ", 
  "MUL ", 
  "DUP2 ", 
  "MSTORE ", 
  "PUSH1 0x04 ", 
  "ADD ", 
  "DUP1 ", 
  "DUP4 ", 
  "DUP2 ", 
  "MSTORE ", 
  "PUSH1 0x20 ", 
  "ADD ", 
  "DUP3 ", 
  "DUP2 ", 
  "MSTORE ", 
  "PUSH1 0x20 ", 
  "ADD ", 
  "SWAP3 ", 
  "POP ", 
  "POP ", 
  "POP ", 
  "PUSH1 0x20 ", 
  "PUSH1 0x40 ", 
  "MLOAD ", 
  "DUP1 ", 
  "DUP4 ", 
  "SUB ", 
  "DUP2 ", 
  "DUP7 ", 
  "DUP1 ", 
  "EXTCODESIZE ", 
  "ISZERO ", 
  "ISZERO ", 
  "PUSH2 0x1923 ", 
  "JUMPI ", 
  "PUSH1 0x00 ", 
  "DUP1 ", 
  "REVERT ", 
  "JUMPDEST ", 
  "GAS ", 
  "DELEGATECALL ", 
  "ISZERO ", 
  "ISZERO ", 
  "PUSH2 0x1930 ", 
  "JUMPI ", 
  "PUSH1 0x00 ", 
  "DUP1 ", 
  "REVERT ", 
  "JUMPDEST ", 
  "POP ", 
  "POP ", 
  "POP ", 
  "PUSH1 0x40 ", 
  "MLOAD ", 
  "DUP1 ", 
  "MLOAD ", 
  "SWAP1 ", 
  "POP ", 
  "PUSH1 0x0a ", 
  "POP ", 
  "DUP2 ", 
  "SWAP1 ", 
  "SSTORE ", 
  "POP ", 
  "PUSH1 0x09 ", 
  "SLOAD ", 
  "PUSH20 0x0000000000000000000000000000000000000001 ", 
  "ISZERO ", 
  "SLOAD ", 
  "PUSH4 0x66098d4f ", 
  "SWAP1 ", 
  "SWAP2 ", 
  "DUP5 ", 
  "PUSH1 0x40 ", 
  "PUSH1 0x12 ", 
  "MLOAD ", 
  "DUP4 ", 
  "PUSH4 0xffffffff ", 
  "PUSH1 0x00 ", 
  "AND ", 
  "PUSH29 0x0100000000000000000000000000000000000000000000000000000000 ", 
  "EQ ", 
  "ISZERO ", 
  "ISZERO ", 
  "ISZERO ", 
  "PUSH2 0x299d ", 
  "DUP1 ", 
  "MUL ", 
  "DUP2 ", 
  "MSTORE ", 
  "PUSH1 0x04 ", 
  "ADD ", 
  "DUP1 ", 
  "DUP4 ", 
  "DUP2 ", 
  "MSTORE ", 
  "PUSH1 0x20 ", 
  "ADD ", 
  "DUP3 ", 
  "DUP2 ", 
  "MSTORE ", 
  "PUSH1 0x20 ", 
  "ADD ", 
  "SWAP3 ", 
  "POP ", 
  "POP ", 
  "POP ", 
  "PUSH1 0x20 ", 
  "PUSH1 0x40 ", 
  "DUP1 ", 
  "MLOAD ", 
  "DUP1 ", 
  "DUP4 ", 
  "SUB ", 
  "DUP2 ", 
  "DUP7 ", 
  "DUP1 ", 
  "EXTCODESIZE ", 
  "ISZERO ", 
  "ISZERO ", 
  "PUSH2 0x19b6 ", 
  "EXP ", 
  "JUMPI ", 
  "PUSH1 0x00 ", 
  "DUP1 ", 
  "REVERT ", 
  "JUMPDEST ", 
  "GAS ", 
  "DELEGATECALL ", 
  "ISZERO ", 
  "ISZERO ", 
  "PUSH2 0x19c3 ", 
  "JUMPI ", 
  "PUSH1 0x00 ", 
  "DUP1 ", 
  "REVERT ", 
  "JUMPDEST ", 
  "POP ", 
  "POP ", 
  "POP ", 
  "PUSH1 0x40 ", 
  "MLOAD ", 
  "DUP1 ", 
  "MLOAD ", 
  "SWAP1 ", 
  "POP ", 
  "PUSH1 0x09 ", 
  "JUMP ", 
  "DUP2 ", 
  "SWAP1 ", 
  "SSTORE ", 
  "POP ", 
  "PUSH1 0x0f ", 
  "PUSH1 0x00 ", 
  "DUP7 ", 
  "PUSH20 0xffffffffffffffffffffffffffffffffffffffff ", 
  "EXP ", 
  "JUMPI ", 
  "PUSH1 0x00 ", 
  "JUMPDEST ", 
  "AND ", 
  "PUSH20 0xffffffffffffffffffffffffffffffffffffffff ", 
  "DUP1 ", 
  "SWAP1 ", 
  "PUSH2 0x2de7 ", 
  "DUP2 ", 
  "AND ", 
  "DUP2 ", 
  "MSTORE ", 
  "PUSH1 0x20 ", 
  "ADD ", 
  "SWAP1 ", 
  "DUP2 ", 
  "MSTORE ", 
  "PUSH1 0x20 ", 
  "DUP4 ", 
  "ADD ", 
  "PUSH1 0x00 ", 
  "SHA3 ", 
  "SLOAD ", 
  "PUSH20 0x0000000000000000000000000000000000000001 ", 
  "DUP4 ", 
  "POP ", 
  "PUSH4 0x66098d4f ", 
  "SWAP1 ", 
  "SWAP2 ", 
  "DUP4 ", 
  "PUSH1 0x40 ", 
  "MLOAD ", 
  "DUP4 ", 
  "PUSH4 0xffffffff ", 
  "AND ", 
  "PUSH29 0x0100000000000000000000000000000000000000000000000000000000 ", 
  "PUSH1 0x03 ", 
  "DUP1 ", 
  "JUMPDEST ", 
  "PUSH4 0x40c10f19 ", 
  "DUP2 ", 
  "MSTORE ", 
  "MUL ", 
  "DUP2 ", 
  "MSTORE ", 
  "PUSH1 0x04 ", 
  "ADD ", 
  "DUP1 ", 
  "DUP4 ", 
  "DUP2 ", 
  "MSTORE ", 
  "PUSH1 0x20 ", 
  "ADD ", 
  "DUP3 ", 
  "DUP2 ", 
  "MSTORE ", 
  "PUSH1 0x20 ", 
  "ADD ", 
  "SWAP3 ", 
  "POP ", 
  "POP ", 
  "POP ", 
  "PUSH1 0x20 ", 
  "PUSH1 0x40 ", 
  "MLOAD ", 
  "DUP1 ", 
  "DUP4 ", 
  "SUB ", 
  "DUP2 ", 
  "DUP7 ", 
  "DUP1 ", 
  "EXTCODESIZE ", 
  "ISZERO ", 
  "ISZERO ", 
  "PUSH2 0x1a86 ", 
  "JUMPI ", 
  "PUSH1 0x00 ", 
  "SLOAD ", 
  "DUP1 ", 
  "REVERT ", 
  "JUMPDEST ", 
  "GAS ", 
  "DELEGATECALL ", 
  "ISZERO ", 
  "ISZERO ", 
  "PUSH2 0x1a93 ", 
  "SLOAD ", 
  "JUMPI ", 
  "PUSH1 0x00 ", 
  "PUSH1 0x00 ", 
  "DUP1 ", 
  "REVERT ", 
  "JUMPDEST ", 
  "POP ", 
  "POP ", 
  "POP ", 
  "PUSH1 0x40 ", 
  "GAS ", 
  "MLOAD ", 
  "DUP1 ", 
  "MLOAD ", 
  "SWAP1 ", 
  "POP ", 
  "PUSH1 0x0f ", 
  "PUSH1 0x00 ", 
  "DUP8 ", 
  "PUSH20 0xffffffffffffffffffffffffffffffffffffffff ", 
  "DUP8 ", 
  "PUSH1 0x01 ", 
  "PUSH1 0x20 ", 
  "PUSH1 0x20 ", 
  "DELEGATECALL ", 
  "AND ", 
  "PUSH20 0xffffffffffffffffffffffffffffffffffffffff ", 
  "PUSH2 0x0100 ", 
  "DUP1 ", 
  "AND ", 
  "DUP2 ", 
  "MSTORE ", 
  "PUSH1 0x20 ", 
  "ADD ", 
  "SWAP1 ", 
  "DUP2 ", 
  "MSTORE ", 
  "PUSH1 0x20 ", 
  "ADD ", 
  "PUSH1 0x00 ", 
  "SHA3 ", 
  "DUP2 ", 
  "SWAP1 ", 
  "SSTORE ", 
  "POP ", 
  "PUSH1 0x10 ", 
  "PUSH1 0x00 ", 
  "PUSH1 0x00 ", 
  "DUP7 ", 
  "PUSH20 0xffffffffffffffffffffffffffffffffffffffff ", 
  "ADD ", 
  "MUL ", 
  "SLOAD ", 
  "AND ", 
  "PUSH20 0xffffffffffffffffffffffffffffffffffffffff ", 
  "ISZERO ", 
  "DUP1 ", 
  "DUP1 ", 
  "AND ", 
  "DUP2 ", 
  "MSTORE ", 
  "PUSH1 0x20 ", 
  "ADD ", 
  "SWAP1 ", 
  "DUP2 ", 
  "MSTORE ", 
  "PUSH1 0x20 ", 
  "ADD ", 
  "PUSH1 0x00 ", 
  "SHA3 ", 
  "SLOAD ", 
  "PUSH20 0x0000000000000000000000000000000000000001 ", 
  "DUP2 ", 
  "AND ", 
  "SWAP1 ", 
  "MUL ", 
  "JUMP ", 
  "DUP4 ", 
  "PUSH20 0xffffffffffffffffffffffffffffffffffffffff ", 
  "PUSH4 0x66098d4f ", 
  "PUSH2 0x2ca0 ", 
  "SWAP1 ", 
  "SWAP2 ", 
  "DUP5 ", 
  "PUSH1 0x40 ", 
  "MLOAD ", 
  "DUP4 ", 
  "PUSH4 0xffffffff ", 
  "AND ", 
  "PUSH29 0x0100000000000000000000000000000000000000000000000000000000 ", 
  "PUSH1 0x20 ", 
  "PUSH2 0x2b93 ", 
  "DUP2 ", 
  "AND ", 
  "MUL ", 
  "DUP2 ", 
  "MSTORE ", 
  "PUSH1 0x04 ", 
  "JUMPI ", 
  "ADD ", 
  "DUP1 ", 
  "DUP4 ", 
  "DUP2 ", 
  "MSTORE ", 
  "PUSH1 0x20 ", 
  "ADD ", 
  "DUP3 ", 
  "DUP2 ", 
  "MSTORE ", 
  "PUSH1 0x20 ", 
  "ADD ", 
  "SWAP3 ", 
  "POP ", 
  "POP ", 
  "POP ", 
  "PUSH1 0x20 ", 
  "PUSH1 0x40 ", 
  "MLOAD ", 
  "DUP1 ", 
  "DUP4 ", 
  "SUB ", 
  "DUP2 ", 
  "DUP7 ", 
  "DUP1 ", 
  "EXTCODESIZE ", 
  "ISZERO ", 
  "ISZERO ", 
  "PUSH2 0x1b93 ", 
  "JUMPI ", 
  "PUSH1 0x00 ", 
  "DUP1 ", 
  "REVERT ", 
  "JUMPDEST ", 
  "GAS ", 
  "DELEGATECALL ", 
  "ISZERO ", 
  "ISZERO ", 
  "PUSH2 0x1ba0 ", 
  "JUMPI ", 
  "PUSH1 0x00 ", 
  "DUP1 ", 
  "REVERT ", 
  "JUMPDEST ", 
  "POP ", 
  "POP ", 
  "POP ", 
  "PUSH1 0x40 ", 
  "MLOAD ", 
  "DUP1 ", 
  "MLOAD ", 
  "SWAP1 ", 
  "POP ", 
  "PUSH1 0x10 ", 
  "PUSH1 0x00 ", 
  "DUP8 ", 
  "PUSH20 0xffffffffffffffffffffffffffffffffffffffff ", 
  "PUSH1 0x00 ", 
  "PUSH1 0x07 ", 
  "MLOAD ", 
  "AND ", 
  "PUSH20 0xffffffffffffffffffffffffffffffffffffffff ", 
  "SWAP1 ", 
  "DUP2 ", 
  "PUSH32 0x48d826081348f5f00e8a33c9ae8ce89ed4c6e88400b585a478bc203d9e8177d3 ", 
  "AND ", 
  "DUP2 ", 
  "MSTORE ", 
  "PUSH1 0x20 ", 
  "ADD ", 
  "SWAP1 ", 
  "DUP2 ", 
  "MSTORE ", 
  "PUSH1 0x20 ", 
  "ADD ", 
  "PUSH1 0x00 ", 
  "SHA3 ", 
  "DUP2 ", 
  "SWAP1 ", 
  "SSTORE ", 
  "POP ", 
  "PUSH2 0x1bf7 ", 
  "DUP6 ", 
  "DUP4 ", 
  "PUSH2 0x35b1 ", 
  "JUMP ", 
  "JUMPDEST ", 
  "PUSH32 0x0396f60aaad038749091d273dc13aaabc63db6e2271c7bad442d5cf25cc43350 ", 
  "SWAP1 ", 
  "DUP4 ", 
  "DUP6 ", 
  "REVERT ", 
  "DUP6 ", 
  "DUP3 ", 
  "DUP5 ", 
  "PUSH1 0x00 ", 
  "PUSH1 0x40 ", 
  "POP ", 
  "MLOAD ", 
  "DUP1 ", 
  "DUP6 ", 
  "PUSH20 0xffffffffffffffffffffffffffffffffffffffff ", 
  "PUSH2 0x0100 ", 
  "AND ", 
  "PUSH20 0xffffffffffffffffffffffffffffffffffffffff ", 
  "DUP2 ", 
  "SWAP1 ", 
  "AND ", 
  "DUP2 ", 
  "MSTORE ", 
  "PUSH1 0x20 ", 
  "ADD ", 
  "DUP5 ", 
  "DUP2 ", 
  "MSTORE ", 
  "PUSH1 0x20 ", 
  "ADD ", 
  "DUP4 ", 
  "DUP2 ", 
  "MSTORE ", 
  "PUSH1 0x20 ", 
  "ADD ", 
  "DUP3 ", 
  "PUSH16 0xffffffffffffffffffffffffffffffff ", 
  "AND ", 
  "DUP2 ", 
  "MSTORE ", 
  "PUSH1 0x20 ", 
  "ADD ", 
  "SWAP5 ", 
  "POP ", 
  "POP ", 
  "POP ", 
  "POP ", 
  "POP ", 
  "PUSH1 0x40 ", 
  "MLOAD ", 
  "DUP1 ", 
  "SWAP2 ", 
  "SUB ", 
  "SWAP1 ", 
  "LOG1 ", 
  "POP ", 
  "POP ", 
  "POP ", 
  "POP ", 
  "POP ", 
  "JUMP ", 
  "JUMPDEST ", 
  "PUSH1 0x13 ", 
  "SLOAD ", 
  "DUP2 ", 
  "JUMP ", 
  "JUMPDEST ", 
  "PUSH1 0x0a ", 
  "SLOAD ", 
  "DUP2 ", 
  "JUMP ", 
  "JUMPDEST ", 
  "PUSH1 0x00 ", 
  "PUSH1 0x01 ", 
  "JUMPDEST ", 
  "SWAP1 ", 
  "POP ", 
  "SWAP1 ", 
  "JUMP ", 
  "JUMPDEST ", 
  "PUSH1 0x04 ", 
  "DUP1 ", 
  "PUSH1 0x07 ", 
  "DUP2 ", 
  "GT ", 
  "ISZERO ", 
  "PUSH2 0x1caf ", 
  "JUMPI ", 
  "ASSERTFAIL ", 
  "JUMPDEST ", 
  "PUSH2 0x1cb7 ", 
  "EXP ", 
  "PUSH2 0x1229 ", 
  "SWAP1 ", 
  "JUMP ", 
  "JUMPDEST ", 
  "PUSH1 0x07 ", 
  "DUP2 ", 
  "GT ", 
  "ISZERO ", 
  "PUSH2 0x1cc2 ", 
  "JUMPI ", 
  "ASSERTFAIL ", 
  "JUMPDEST ", 
  "EQ ", 
  "ISZERO ", 
  "ISZERO ", 
  "PUSH2 0x1cce ", 
  "PUSH2 0x0100 ", 
  "JUMPI ", 
  "PUSH1 0x00 ", 
  "DUP1 ", 
  "REVERT ", 
  "JUMPDEST ", 
  "PUSH1 0x00 ", 
  "DUP1 ", 
  "SWAP1 ", 
  "SLOAD ", 
  "SWAP1 ", 
  "PUSH2 0x0100 ", 
  "EXP ", 
  "SWAP1 ", 
  "DIV ", 
  "PUSH20 0xffffffffffffffffffffffffffffffffffffffff ", 
  "PUSH2 0x0100 ", 
  "SWAP1 ", 
  "DIV ", 
  "SWAP1 ", 
  "ISZERO ", 
  "PUSH1 0xff ", 
  "AND ", 
  "PUSH20 0xffffffffffffffffffffffffffffffffffffffff ", 
  "DUP1 ", 
  "AND ", 
  "SWAP1 ", 
  "PUSH1 0x0e ", 
  "AND ", 
  "CALLER ", 
  "PUSH20 0xffffffffffffffffffffffffffffffffffffffff ", 
  "PUSH1 0x02 ", 
  "CALLER ", 
  "SWAP1 ", 
  "SLOAD ", 
  "AND ", 
  "EQ ", 
  "ISZERO ", 
  "ISZERO ", 
  "PUSH2 0x1d29 ", 
  "JUMPI ", 
  "PUSH1 0x00 ", 
  "DUP1 ", 
  "REVERT ", 
  "JUMPDEST ", 
  "PUSH1 0x00 ", 
  "PUSH1 0x14 ", 
  "SWAP1 ", 
  "SLOAD ", 
  "SWAP1 ", 
  "PUSH2 0x0100 ", 
  "DUP5 ", 
  "EXP ", 
  "SWAP1 ", 
  "DIV ", 
  "PUSH1 0xff ", 
  "AND ", 
  "ISZERO ", 
  "PUSH2 0x1d43 ", 
  "JUMPI ", 
  "PUSH1 0x00 ", 
  "DUP1 ", 
  "REVERT ", 
  "JUMPDEST ", 
  "PUSH1 0x0e ", 
  "DIV ", 
  "PUSH1 0x00 ", 
  "SWAP1 ", 
  "SWAP1 ", 
  "SLOAD ", 
  "SWAP1 ", 
  "PUSH2 0x0100 ", 
  "SWAP2 ", 
  "EXP ", 
  "SWAP1 ", 
  "DIV ", 
  "PUSH1 0xff ", 
  "AND ", 
  "ISZERO ", 
  "PUSH2 0x1d5d ", 
  "AND ", 
  "JUMPI ", 
  "PUSH1 0x00 ", 
  "DUP1 ", 
  "REVERT ", 
  "JUMPDEST ", 
  "PUSH1 0x00 ", 
  "PUSH1 0x04 ", 
  "PUSH1 0x00 ", 
  "SWAP1 ", 
  "SLOAD ", 
  "SWAP1 ", 
  "PUSH2 0x0100 ", 
  "PUSH1 0x03 ", 
  "EXP ", 
  "SWAP1 ", 
  "DIV ", 
  "PUSH20 0xffffffffffffffffffffffffffffffffffffffff ", 
  "PUSH4 0xffffffff ", 
  "JUMPDEST ", 
  "SWAP1 ", 
  "PUSH1 0x00 ", 
  "SLOAD ", 
  "PUSH2 0x0100 ", 
  "SWAP1 ", 
  "AND ", 
  "PUSH20 0xffffffffffffffffffffffffffffffffffffffff ", 
  "PUSH2 0x0100 ", 
  "JUMP ", 
  "REVERT ", 
  "POP ", 
  "AND ", 
  "SWAP1 ", 
  "REVERT ", 
  "AND ", 
  "EQ ", 
  "ISZERO ", 
  "ISZERO ", 
  "PUSH2 0x1e35 ", 
  "JUMPI ", 
  "PUSH1 0x04 ", 
  "PUSH1 0x00 ", 
  "SWAP1 ", 
  "SLOAD ", 
  "SWAP1 ", 
  "PUSH2 0x0100 ", 
  "JUMPDEST ", 
  "EXP ", 
  "SWAP1 ", 
  "DIV ", 
  "PUSH20 0xffffffffffffffffffffffffffffffffffffffff ", 
  "AND ", 
  "PUSH20 0xffffffffffffffffffffffffffffffffffffffff ", 
  "DUP2 ", 
  "PUSH20 0xffffffffffffffffffffffffffffffffffffffff ", 
  "SLOAD ", 
  "AND ", 
  "PUSH4 0x0bf318a3 ", 
  "JUMPDEST ", 
  "PUSH1 0x40 ", 
  "MLOAD ", 
  "DUP2 ", 
  "PUSH4 0xffffffff ", 
  "PUSH1 0x00 ", 
  "SLOAD ", 
  "AND ", 
  "PUSH29 0x0100000000000000000000000000000000000000000000000000000000 ", 
  "POP ", 
  "PUSH20 0xffffffffffffffffffffffffffffffffffffffff ", 
  "PUSH1 0x00 ", 
  "MUL ", 
  "DUP2 ", 
  "MSTORE ", 
  "PUSH1 0x04 ", 
  "ADD ", 
  "PUSH1 0x00 ", 
  "PUSH1 0x40 ", 
  "MLOAD ", 
  "DUP1 ", 
  "DUP4 ", 
  "SUB ", 
  "DUP2 ", 
  "PUSH1 0x00 ", 
  "DUP8 ", 
  "DUP1 ", 
  "EXTCODESIZE ", 
  "ISZERO ", 
  "ISZERO ", 
  "PUSH2 0x1e24 ", 
  "JUMPI ", 
  "PUSH1 0x00 ", 
  "DUP1 ", 
  "REVERT ", 
  "JUMPDEST ", 
  "GAS ", 
  "CALL ", 
  "ISZERO ", 
  "ISZERO ", 
  "PUSH2 0x1e31 ", 
  "JUMPI ", 
  "PUSH1 0x00 ", 
  "DUP1 ", 
  "REVERT ", 
  "JUMPDEST ", 
  "POP ", 
  "POP ", 
  "POP ", 
  "JUMPDEST ", 
  "PUSH1 0x01 ", 
  "ISZERO ", 
  "PUSH1 0x0e ", 
  "PUSH1 0x00 ", 
  "MLOAD ", 
  "PUSH2 0x0100 ", 
  "EXP ", 
  "DUP2 ", 
  "SLOAD ", 
  "DUP2 ", 
  "PUSH1 0xff ", 
  "MUL ", 
  "NOT ", 
  "AND ", 
  "SWAP1 ", 
  "DUP4 ", 
  "ISZERO ", 
  "ISZERO ", 
  "MUL ", 
  "OR ", 
  "SWAP1 ", 
  "SSTORE ", 
  "POP ", 
  "POP ", 
  "JUMP ", 
  "JUMPDEST ", 
  "PUSH1 0x00 ", 
  "ISZERO ", 
  "DUP1 ", 
  "SWAP1 ", 
  "SLOAD ", 
  "SWAP1 ", 
  "PUSH2 0x0100 ", 
  "PUSH1 0x04 ", 
  "EXP ", 
  "SWAP1 ", 
  "DIV ", 
  "PUSH20 0xffffffffffffffffffffffffffffffffffffffff ", 
  "DUP2 ", 
  "ADD ", 
  "MSTORE ", 
  "PUSH1 0x20 ", 
  "DUP4 ", 
  "AND ", 
  "PUSH20 0xffffffffffffffffffffffffffffffffffffffff ", 
  "PUSH2 0x0100 ", 
  "DUP2 ", 
  "ADD ", 
  "MSTORE ", 
  "DUP4 ", 
  "PUSH1 0x20 ", 
  "ISZERO ", 
  "AND ", 
  "CALLER ", 
  "PUSH20 0xffffffffffffffffffffffffffffffffffffffff ", 
  "ADD ", 
  "ISZERO ", 
  "EXP ", 
  "DUP2 ", 
  "DUP2 ", 
  "AND ", 
  "EQ ", 
  "ISZERO ", 
  "ISZERO ", 
  "PUSH2 0x1eae ", 
  "MSTORE ", 
  "JUMPI ", 
  "PUSH1 0x00 ", 
  "DUP1 ", 
  "REVERT ", 
  "JUMPDEST ", 
  "DUP1 ", 
  "PUSH1 0x03 ", 
  "PUSH1 0x00 ", 
  "PUSH2 0x0100 ", 
  "ADD ", 
  "SWAP1 ", 
  "EXP ", 
  "DUP2 ", 
  "SLOAD ", 
  "DUP2 ", 
  "PUSH20 0xffffffffffffffffffffffffffffffffffffffff ", 
  "DUP3 ", 
  "POP ", 
  "POP ", 
  "POP ", 
  "MUL ", 
  "NOT ", 
  "AND ", 
  "SWAP1 ", 
  "DUP4 ", 
  "PUSH20 0xffffffffffffffffffffffffffffffffffffffff ", 
  "JUMPDEST ", 
  "PUSH20 0xffffffffffffffffffffffffffffffffffffffff ", 
  "PUSH1 0x40 ", 
  "AND ", 
  "MUL ", 
  "OR ", 
  "SWAP1 ", 
  "SSTORE ", 
  "POP ", 
  "PUSH1 0x03 ", 
  "DUP1 ", 
  "PUSH1 0x00 ", 
  "SWAP1 ", 
  "SLOAD ", 
  "SWAP1 ", 
  "PUSH2 0x0100 ", 
  "EXP ", 
  "SWAP1 ", 
  "DIV ", 
  "PUSH20 0xffffffffffffffffffffffffffffffffffffffff ", 
  "REVERT ", 
  "DUP7 ", 
  "DUP1 ", 
  "DUP1 ", 
  "PUSH2 0x0100 ", 
  "AND ", 
  "PUSH20 0xffffffffffffffffffffffffffffffffffffffff ", 
  "ISZERO ", 
  "ISZERO ", 
  "PUSH2 0x2539 ", 
  "AND ", 
  "PUSH4 0x04bbc255 ", 
  "PUSH1 0x40 ", 
  "MLOAD ", 
  "DUP2 ", 
  "PUSH4 0xffffffff ", 
  "AND ", 
  "PUSH29 0x0100000000000000000000000000000000000000000000000000000000 ", 
  "PUSH1 0x00 ", 
  "AND ", 
  "PUSH1 0xff ", 
  "PUSH20 0xffffffffffffffffffffffffffffffffffffffff ", 
  "REVERT ", 
  "SWAP1 ", 
  "MUL ", 
  "DUP2 ", 
  "MSTORE ", 
  "PUSH1 0x04 ", 
  "ADD ", 
  "PUSH1 0x20 ", 
  "GAS ", 
  "PUSH1 0x40 ", 
  "MLOAD ", 
  "DUP1 ", 
  "DUP4 ", 
  "SUB ", 
  "DUP2 ", 
  "PUSH1 0x00 ", 
  "DUP8 ", 
  "DUP1 ", 
  "EXTCODESIZE ", 
  "ISZERO ", 
  "ISZERO ", 
  "PUSH2 0x1f74 ", 
  "DUP1 ", 
  "JUMPI ", 
  "PUSH1 0x00 ", 
  "DUP1 ", 
  "REVERT ", 
  "JUMPDEST ", 
  "GAS ", 
  "CALL ", 
  "ISZERO ", 
  "ISZERO ", 
  "PUSH2 0x1f81 ", 
  "JUMPI ", 
  "PUSH1 0x00 ", 
  "DUP1 ", 
  "REVERT ", 
  "JUMPDEST ", 
  "POP ", 
  "POP ", 
  "POP ", 
  "PUSH1 0x40 ", 
  "MLOAD ", 
  "DUP1 ", 
  "MLOAD ", 
  "SWAP1 ", 
  "POP ", 
  "ISZERO ", 
  "ISZERO ", 
  "PUSH2 0x1f96 ", 
  "JUMPI ", 
  "PUSH1 0x00 ", 
  "DUP1 ", 
  "REVERT ", 
  "JUMPDEST ", 
  "POP ", 
  "JUMP ", 
  "JUMPDEST ", 
  "PUSH1 0x09 ", 
  "SLOAD ", 
  "DUP2 ", 
  "JUMP ", 
  "JUMPDEST ", 
  "PUSH1 0x00 ", 
  "PUSH1 0x07 ", 
  "DUP1 ", 
  "PUSH1 0x07 ", 
  "DIV ", 
  "DUP2 ", 
  "GT ", 
  "ISZERO ", 
  "PUSH2 0x1faf ", 
  "POP ", 
  "JUMPI ", 
  "ASSERTFAIL ", 
  "JUMPDEST ", 
  "PUSH2 0x1fb7 ", 
  "PUSH2 0x1229 ", 
  "JUMP ", 
  "JUMPDEST ", 
  "PUSH1 0x07 ", 
  "DUP2 ", 
  "GT ", 
  "ISZERO ", 
  "PUSH2 0x1fc2 ", 
  "JUMPI ", 
  "ASSERTFAIL ", 
  "JUMPDEST ", 
  "EQ ", 
  "ISZERO ", 
  "ISZERO ", 
  "PUSH2 0x1fce ", 
  "AND ", 
  "JUMPI ", 
  "PUSH1 0x00 ", 
  "DUP1 ", 
  "REVERT ", 
  "JUMPDEST ", 
  "PUSH1 0x0f ", 
  "PUSH1 0x00 ", 
  "CALLER ", 
  "PUSH20 0xffffffffffffffffffffffffffffffffffffffff ", 
  "SWAP1 ", 
  "DUP2 ", 
  "AND ", 
  "PUSH20 0xffffffffffffffffffffffffffffffffffffffff ", 
  "POP ", 
  "POP ", 
  "SWAP1 ", 
  "PUSH1 0x40 ", 
  "ADD ", 
  "POP ", 
  "AND "
 ], 
 "overflow": "\n../contractSrc/0xa5ca78d849fa2b1cd4f37e81e99f6c5cc6c92a7e.sol:RelaunchedCrowdsale:992:5\nweiRaised += _weiAmount\n^\n../contractSrc/0xa5ca78d849fa2b1cd4f37e81e99f6c5cc6c92a7e.sol:RelaunchedCrowdsale:381:8\ninvestorCount++\n^\n../contractSrc/0xa5ca78d849fa2b1cd4f37e81e99f6c5cc6c92a7e.sol:RelaunchedCrowdsale:990:5\ntokenAmountOf[_addr] += _tokenAmount\n^\n../contractSrc/0xa5ca78d849fa2b1cd4f37e81e99f6c5cc6c92a7e.sol:RelaunchedCrowdsale:986:7\ninvestorCount++\n^\n../contractSrc/0xa5ca78d849fa2b1cd4f37e81e99f6c5cc6c92a7e.sol:RelaunchedCrowdsale:993:5\ntokensSold += _tokenAmount\n^\n../contractSrc/0xa5ca78d849fa2b1cd4f37e81e99f6c5cc6c92a7e.sol:RelaunchedCrowdsale:989:5\ninvestedAmountOf[_addr] += _weiAmount\n^", 
 "money_concurrency": false, 
 "truncation": false
},"SafeMath":{
 "execution_paths": "1", 
 "callstack": false, 
 "reentrancy": false, 
 "modulo": false, 
 "division": false, 
 "execution_time": "0.00883889198303", 
 "signedness": false, 
 "evm_code_coverage": "100.0", 
 "underflow": false, 
 "time_dependency": false, 
 "assertion_failure": false, 
 "timeout": false, 
 "dead_code": [], 
 "overflow": false, 
 "money_concurrency": false, 
 "truncation": false
},"SafeMathLib":{
 "execution_paths": "12", 
 "callstack": false, 
 "reentrancy": false, 
 "modulo": false, 
 "division": false, 
 "execution_time": "7.98384094238", 
 "signedness": false, 
 "evm_code_coverage": "99.7", 
 "underflow": false, 
 "time_dependency": false, 
 "assertion_failure": false, 
 "timeout": false, 
 "dead_code": [
  "STOP "
 ], 
 "overflow": false, 
 "money_concurrency": false, 
 "truncation": false
},"StandardToken":{
 "execution_paths": "27", 
 "callstack": false, 
 "reentrancy": false, 
 "modulo": false, 
 "division": false, 
 "execution_time": "1.61515402794", 
 "signedness": false, 
 "evm_code_coverage": "99.9", 
 "underflow": false, 
 "time_dependency": false, 
 "assertion_failure": false, 
 "timeout": false, 
 "dead_code": [
  "STOP "
 ], 
 "overflow": false, 
 "money_concurrency": false, 
 "truncation": false
}}